<?xml version='1.0' encoding='utf-8'?>
<tv>
  <channel id="Channel-4-UK">
    <display-name>Channel 4</display-name>
    <icon src="https://thefilmtuition.com/tvlogo/Channel-4-UK.png" />
  </channel><programme channel="Channel-4-UK" start="20260419000000 +0500" stop="20260419010000 +0500">
    <title>World's Most Secret Hotels</title>
    <sub-title />
    <desc>A journey to discover the world's most extraordinary hotels, including a brutalist lodge in Bolivia, a mirrored resort on a Norwegian fjord and an art deco hotel in the Pyrenees.</desc>
    <category lang="en">Entertainment</category>
    <category lang="en">Travel</category>
    <language>en</language>
    <icon src="https://images.metadata.sky.com/pd-image/ae462f52-c117-40dc-afbc-ea39cad65d58/16-9" />
  </programme><programme channel="Channel-4-UK" start="20260419010000 +0500" stop="20260419031000 +0500">
    <title>Plane</title>
    <sub-title />
    <desc>Action thriller starring Gerard Butler as an airline pilot who becomes a one-man army after crash landing on an island overrun by bad guys. To survive, he's gonna have to wing it.</desc>
    <date>2023</date>
    <category lang="en">Movie</category>
    <category lang="en">Action</category>
    <language>en</language>
    <icon src="https://images.metadata.sky.com/pd-image/d2779044-0421-4ba9-be8c-8fc1defe585b/16-9" />
    <rating system="UK">
      <value>15</value>
    </rating>
  </programme><programme channel="Channel-4-UK" start="20260419031000 +0500" stop="20260419045000 +0500">
    <title>Commando</title>
    <sub-title />
    <desc>Thriller starring Arnold Schwarzenegger. To free his kidnapped daughter, an ex US commando must agree to assassinate a South American president. But he's not as pliant as he seems..</desc>
    <date>1985</date>
    <category lang="en">Movie</category>
    <category lang="en">Action</category>
    <language>en</language>
    <icon src="https://images.metadata.sky.com/pd-image/c71ae7ea-ae92-4f96-b78d-1c6ceec5182d/16-9" />
    <rating system="UK">
      <value>18</value>
    </rating>
  </programme><programme channel="Channel-4-UK" start="20260419045000 +0500" stop="20260419054500 +0500">
    <title>Taskmaster</title>
    <sub-title />
    <desc>In a particularly active episode, Armando Iannucci performs a daring stunt, Kumail Nanjiani moves bowling pins with oven gloves, and Joanna Page unwisely attempts a handstand.</desc>
    <category lang="en">Entertainment</category>
    <category lang="en">Game Show</category>
    <language>en</language>
    <icon src="https://images.metadata.sky.com/pd-image/3c932574-a215-4bb7-8395-fc12bde08ad0/16-9" />
  </programme><programme channel="Channel-4-UK" start="20260419054500 +0500" stop="20260419063500 +0500">
    <title>Ramsay's Kitchen Nightmares USA</title>
    <sub-title>Casa Roma</sub-title>
    <desc>Gordon visits Casa Roma, the oldest restaurant in Lancaster, California. Although the bar is a success, the restaurant is failing and has had 20 chefs in two years.</desc>
    <category lang="en">Entertainment</category>
    <category lang="en">Cooking</category>
    <language>en</language>
    <icon src="https://images.metadata.sky.com/pd-image/464e87ed-6111-4597-b8b4-9ef2a464cd97/16-9" />
  </programme><programme channel="Channel-4-UK" start="20260419063500 +0500" stop="20260419073000 +0500">
    <title>Couples Come Dine with Me</title>
    <sub-title />
    <desc>In and around Edinburgh, there are some hard-to-digest jokes, a cat hair catastrophe and a boy band revelation, as three couples put their hosting skills to the ultimate test.</desc>
    <category lang="en">Entertainment</category>
    <category lang="en">Cooking</category>
    <language>en</language>
    <icon src="https://images.metadata.sky.com/pd-image/6b6ac13b-1c18-44f4-9c6c-99828b2092fc/16-9" />
  </programme><programme channel="Channel-4-UK" start="20260419073000 +0500" stop="20260419082500 +0500">
    <title>George Clarke's Old House New Home</title>
    <sub-title />
    <desc>George visits a handsome, turn-of-the-century terrace home, whose new owners are set on a monochrome colour scheme, and a workshop that makes antique-effect mirrors.</desc>
    <category lang="en">Entertainment</category>
    <category lang="en">Lifestyles</category>
    <language>en</language>
    <icon src="https://images.metadata.sky.com/pd-image/3cc6260b-ab9c-49f1-be3c-1e5227aa3f16/16-9" />
  </programme><programme channel="Channel-4-UK" start="20260419082500 +0500" stop="20260419085000 +0500">
    <title>The Simpsons</title>
    <sub-title>Another Simpsons Clip Show</sub-title>
    <desc>Inspired by the movie The Bridges of Madison County, Marge sits the family down to discuss tales of love. Guest starring Michelle Pfeiffer.</desc>
    <category lang="en">Entertainment</category>
    <category lang="en">Animation</category>
    <language>en</language>
    <icon src="https://images.metadata.sky.com/pd-image/64b5219b-d7a9-4c56-abac-612ae5e54aad/16-9" />
  </programme><programme channel="Channel-4-UK" start="20260419085000 +0500" stop="20260419091000 +0500">
    <title>The Simpsons</title>
    <sub-title>Black-Eyed, Please</sub-title>
    <desc>Flanders loses his cool when his laid-back parents start to prefer Homer's company to his own. Lisa is bullied by her new substitute teacher (Tina Fey).</desc>
    <category lang="en">Entertainment</category>
    <category lang="en">Animation</category>
    <language>en</language>
    <icon src="https://images.metadata.sky.com/pd-image/586419a2-0edb-4032-b67b-56f4d1822ada/16-9" />
  </programme><programme channel="Channel-4-UK" start="20260419091000 +0500" stop="20260419093500 +0500">
    <title>The Simpsons</title>
    <sub-title>Dark Knight Court</sub-title>
    <desc>When Bart's accused of playing a prank on the school marching band - a prank he says he didn't commit - Lisa must step in to defend her brother in court.</desc>
    <category lang="en">Entertainment</category>
    <category lang="en">Animation</category>
    <language>en</language>
    <icon src="https://images.metadata.sky.com/pd-image/cc8b5ac5-cd0f-4036-ade6-6f98cb7bde9c/16-9" />
  </programme><programme channel="Channel-4-UK" start="20260419093500 +0500" stop="20260419100000 +0500">
    <title>The Simpsons</title>
    <sub-title>Pulpit Friction</sub-title>
    <desc>A trendy new reverend recruits Homer as a deacon. Dry cleaners accidentally swap Marge's wedding dress for one of Krusty's clown costumes.</desc>
    <category lang="en">Entertainment</category>
    <category lang="en">Animation</category>
    <language>en</language>
    <icon src="https://images.metadata.sky.com/pd-image/06856ca4-b919-4e26-9804-60b8e61e8c5f/16-9" />
  </programme><programme channel="Channel-4-UK" start="20260419100000 +0500" stop="20260419102500 +0500">
    <title>The King of Queens</title>
    <sub-title>Kirbed Enthusiasm</sub-title>
    <desc>Doug bows to pressure to start playing American football again, to help with his fitness levels.</desc>
    <category lang="en">Entertainment</category>
    <category lang="en">Comedy</category>
    <language>en</language>
    <icon src="https://images.metadata.sky.com/pd-image/21ebc923-3b39-4d0f-bf14-3a264c089c4c/16-9" />
  </programme><programme channel="Channel-4-UK" start="20260419102500 +0500" stop="20260419105000 +0500">
    <title>The King of Queens</title>
    <sub-title>Business Affairs</sub-title>
    <desc>Doug is jealous of Carrie's close relationship with a gay colleague. Arthur's jealous of a dog.</desc>
    <category lang="en">Entertainment</category>
    <category lang="en">Comedy</category>
    <language>en</language>
    <icon src="https://images.metadata.sky.com/pd-image/2d417476-8442-4dae-9ed5-4377184512a5/16-9" />
  </programme><programme channel="Channel-4-UK" start="20260419105000 +0500" stop="20260419111500 +0500">
    <title>The King of Queens</title>
    <sub-title>Flame Resistant</sub-title>
    <desc>Carrie gets jealous of Doug's ex-girlfriend's relationship with Doug's mother.</desc>
    <category lang="en">Entertainment</category>
    <category lang="en">Comedy</category>
    <language>en</language>
    <icon src="https://images.metadata.sky.com/pd-image/9786f032-9971-40a4-8c05-acf6afa635ac/16-9" />
  </programme><programme channel="Channel-4-UK" start="20260419111500 +0500" stop="20260419114000 +0500">
    <title>The King of Queens</title>
    <sub-title>Flash Photography</sub-title>
    <desc>Doug regrets taking a dirty photo at a wedding.</desc>
    <category lang="en">Entertainment</category>
    <category lang="en">Comedy</category>
    <language>en</language>
    <icon src="https://images.metadata.sky.com/pd-image/2ee9b629-1ae7-49af-83cc-fa220a1d8ba8/16-9" />
  </programme><programme channel="Channel-4-UK" start="20260419114000 +0500" stop="20260419120500 +0500">
    <title>Everybody Loves Raymond</title>
    <sub-title>The Family Bed</sub-title>
    <desc>Ally's constantly getting into bed with her parents, complaining about monsters in her room. Sleep-deprived Ray tries everything to solve the problem.</desc>
    <category lang="en">Entertainment</category>
    <category lang="en">Comedy</category>
    <language>en</language>
    <icon src="https://images.metadata.sky.com/pd-image/fc190a8a-eae1-4955-90e8-a30c5cbd2ab7/16-9" />
  </programme><programme channel="Channel-4-UK" start="20260419120500 +0500" stop="20260419123000 +0500">
    <title>Everybody Loves Raymond</title>
    <sub-title>Good Girls</sub-title>
    <desc>Debra discovers that her mother-in-law prefers Robert's girlfriend solely on the basis that she's a 'good girl', making Debra wonder what exactly a 'good girl' is.</desc>
    <category lang="en">Entertainment</category>
    <category lang="en">Comedy</category>
    <language>en</language>
    <icon src="https://images.metadata.sky.com/pd-image/6ff452aa-a4b3-4d34-9b45-c3a67a1805b1/16-9" />
  </programme><programme channel="Channel-4-UK" start="20260419123000 +0500" stop="20260419130000 +0500">
    <title>Everybody Loves Raymond</title>
    <sub-title>T-Ball</sub-title>
    <desc>Debra's upset when Ray fails to back her up in an argument with a competitive parent about 'unapproved' pretzels at Ally's little league game.</desc>
    <category lang="en">Entertainment</category>
    <category lang="en">Comedy</category>
    <language>en</language>
    <icon src="https://images.metadata.sky.com/pd-image/be521bed-a90a-4c59-a850-c9507e216a89/16-9" />
  </programme><programme channel="Channel-4-UK" start="20260419130000 +0500" stop="20260419133000 +0500">
    <title>Frasier</title>
    <sub-title />
    <desc>Don't Go Breaking My Heart (Part 3/3): Frasier's driven round the bend by the new lease of life that Niles has acquired following his midlife crisis.</desc>
    <category lang="en">Entertainment</category>
    <category lang="en">Comedy</category>
    <language>en</language>
    <icon src="https://images.metadata.sky.com/pd-image/ac50d555-4d84-4959-8be5-2f14753f05be/16-9" />
  </programme><programme channel="Channel-4-UK" start="20260419133000 +0500" stop="20260419140000 +0500">
    <title>Frasier</title>
    <sub-title>We Two Kings</sub-title>
    <desc>Christmas is coming and so, it seems, is a Crane family feud. Niles and Daphne want to hold the family get-together, but Frasier decides that he'll host too..</desc>
    <category lang="en">Entertainment</category>
    <category lang="en">Comedy</category>
    <language>en</language>
    <icon src="https://images.metadata.sky.com/pd-image/e7328f76-2e79-4ec9-a880-4d631a22fd98/16-9" />
  </programme><programme channel="Channel-4-UK" start="20260419140000 +0500" stop="20260419170000 +0500">
    <title>Live: Sunday Brunch</title>
    <sub-title />
    <desc>Alex James talks about the Big Feastival 2026. SNL UK regulars Paddy Young and Ania Magliano chat about the show. Plus: Tyler West, Chloe Burrows, Damien Molony, Jessie Ware and Skindred.</desc>
    <category lang="en">Entertainment</category>
    <category lang="en">Magazine</category>
    <language>en</language>
    <icon src="https://images.metadata.sky.com/pd-image/2e32eefa-776e-411e-ab87-eac57223e779/16-9" />
  </programme><programme channel="Channel-4-UK" start="20260419170000 +0500" stop="20260419173000 +0500">
    <title>The Simpsons</title>
    <sub-title>The Saga of Carl</sub-title>
    <desc>Homer, Moe, Lenny and Carl win the lottery, but Carl runs off to Iceland with the winnings.</desc>
    <category lang="en">Entertainment</category>
    <category lang="en">Animation</category>
    <language>en</language>
    <icon src="https://images.metadata.sky.com/pd-image/9fd19c90-e29e-47fd-9794-135740469e97/16-9" />
  </programme><programme channel="Channel-4-UK" start="20260419173000 +0500" stop="20260419180000 +0500">
    <title>The Simpsons</title>
    <sub-title>Dangers on a Train</sub-title>
    <desc>While she's browsing for wedding anniversary cakes, Marge stumbles across a website for married people who want to have affairs.</desc>
    <category lang="en">Entertainment</category>
    <category lang="en">Animation</category>
    <language>en</language>
    <icon src="https://images.metadata.sky.com/pd-image/9e1bf6d4-ce2a-4a53-a4e5-759f39f4d85a/16-9" />
  </programme><programme channel="Channel-4-UK" start="20260419180000 +0500" stop="20260419183000 +0500">
    <title>The Simpsons</title>
    <sub-title>The Fabulous Faker Boy</sub-title>
    <desc>Bart doesn't want to go to piano lessons, until he meets his beautiful teacher... Homer loses the last two hairs on his head.</desc>
    <category lang="en">Entertainment</category>
    <category lang="en">Animation</category>
    <language>en</language>
    <icon src="https://images.metadata.sky.com/pd-image/ab670e40-76cf-4645-9d69-662f704f924a/16-9" />
  </programme><programme channel="Channel-4-UK" start="20260419183000 +0500" stop="20260419193500 +0500">
    <title>George Clarke's Amazing Spaces</title>
    <sub-title />
    <desc>A touring theatre performer has an ingenious plan to keep the show on the road... quite literally! And George and Will complete their ambitious secret magical garden studio flat.</desc>
    <category lang="en">Entertainment</category>
    <category lang="en">Lifestyles</category>
    <language>en</language>
    <icon src="https://images.metadata.sky.com/pd-image/ce4c9743-c7a4-35aa-93ee-a5fbc6072f09/16-9" />
  </programme><programme channel="Channel-4-UK" start="20260419193500 +0500" stop="20260419204000 +0500">
    <title>Sailing the Shipping Forecast with The Rev Richard Coles</title>
    <sub-title />
    <desc>Richard meets the rebels and risk takers of Thames, barges about on a floating bakery and returns to his Communards youth.</desc>
    <category lang="en">Entertainment</category>
    <category lang="en">Travel</category>
    <language>en</language>
    <icon src="https://images.metadata.sky.com/pd-image/8f8e2f92-4f7a-4ab0-a7f5-aa1caf9c6979/16-9" />
  </programme><programme channel="Channel-4-UK" start="20260419204000 +0500" stop="20260419214000 +0500">
    <title>Our Tiny Islands</title>
    <sub-title />
    <desc>We run around all five isles of Scilly, meet royalty on Piel Island, get spiritual on Bardsey Island and visit extremely remote St Kilda.</desc>
    <category lang="en">Entertainment</category>
    <category lang="en">Lifestyles</category>
    <language>en</language>
    <icon src="https://images.metadata.sky.com/pd-image/67373077-2d56-3c47-95e8-97f84fe8f523/16-9" />
  </programme><programme channel="Channel-4-UK" start="20260419214000 +0500" stop="20260419221000 +0500">
    <title>Devon and Cornwall</title>
    <sub-title />
    <desc>In the Exmoor foothills, farmers Rob and Sarah Taylor prepare their native ponies for the show season. And can Cornwall's South West Coastal Path be saved from the threat of erosion.</desc>
    <category lang="en">Entertainment</category>
    <category lang="en">Factual</category>
    <language>en</language>
    <icon src="https://images.metadata.sky.com/pd-image/a0f23c93-2811-4bd2-9ac4-262a18243ad1/16-9" />
  </programme><programme channel="Channel-4-UK" start="20260419221000 +0500" stop="20260419224000 +0500">
    <title>Channel 4 News</title>
    <sub-title />
    <desc>Channel 4's flagship news programme. Including the weather.</desc>
    <category lang="en">News &amp; Documentary</category>
    <category lang="en">News</category>
    <language>en</language>
    <icon src="https://images.metadata.sky.com/pd-image/117da670-7fd6-421c-9964-dd3ad2fdc236/16-9" />
  </programme><programme channel="Channel-4-UK" start="20260419224000 +0500" stop="20260419234000 +0500">
    <title>Inside the World's Most Luxurious Yachts</title>
    <sub-title />
    <desc>A voyage behind the scenes of the status-symbol superyachts belonging to some of the world's wealthiest movers and shakers, from Monaco to the Netherlands.</desc>
    <category lang="en">Entertainment</category>
    <category lang="en">Lifestyles</category>
    <language>en</language>
    <icon src="https://images.metadata.sky.com/pd-image/3a4fe8fd-0f90-4e65-a3b2-307a0bd56695/16-9" />
  </programme><programme channel="Channel-4-UK" start="20260419234000 +0500" stop="20260420010000 +0500">
    <title>The Great Celebrity Bake Off for Stand Up To Cancer</title>
    <sub-title />
    <desc>It's a spouse and sibling rivalry, as Chris and Rosie Ramsey and Scarlette and Stuart Douglas take each other on and recreate career highlights in cake.</desc>
    <category lang="en">Entertainment</category>
    <category lang="en">Cooking</category>
    <language>en</language>
    <icon src="https://images.metadata.sky.com/pd-image/06bf9ffd-786f-4876-b43d-e060ea09c245/16-9" />
  </programme><programme channel="Channel-4-UK" start="20260420010000 +0500" stop="20260420020000 +0500">
    <title>Your Song</title>
    <sub-title />
    <desc>Edinburgh locals perform the one song that tells their story - from the tune a 22-year-old played at his mum's funeral to the Zach Bryan track that helped an ex-soldier with his PTSD.</desc>
    <category lang="en">Entertainment</category>
    <category lang="en">Factual</category>
    <language>en</language>
    <icon src="https://images.metadata.sky.com/pd-image/10806ea5-f22a-4244-bbcc-64b3d06ff449/16-9" />
  </programme><programme channel="Channel-4-UK" start="20260420020000 +0500" stop="20260420030000 +0500">
    <title>Gogglebox</title>
    <sub-title />
    <desc>The Goggleboxers watch Secret Garden, Love on the Spectrum, Celebrity Bridge of Lies, Conspiracies and Coverups and the Housemaid.</desc>
    <category lang="en">Entertainment</category>
    <category lang="en">Factual</category>
    <language>en</language>
    <icon src="https://images.metadata.sky.com/pd-image/4332967d-ce2b-484e-9d6c-f84bb0a7b9a1/16-9" />
  </programme><programme channel="Channel-4-UK" start="20260420030000 +0500" stop="20260420040000 +0500">
    <title>First Dates</title>
    <sub-title />
    <desc>A hair stylist meets a nutritionist with a bit of 'swag'. A conspiracy theorist is matched with a science teacher who also wrestles. And an opera singer serenades his date.</desc>
    <category lang="en">Entertainment</category>
    <category lang="en">Factual</category>
    <language>en</language>
    <icon src="https://images.metadata.sky.com/pd-image/3443be49-0145-4d7c-9ed3-6d824ffc9b4d/16-9" />
  </programme><programme channel="Channel-4-UK" start="20260420040000 +0500" stop="20260420045000 +0500">
    <title>Gordon Ramsay's Secret Service</title>
    <sub-title>Parthenon</sub-title>
    <desc>Gordon Ramsay infiltrates struggling restaurants with the help of a secret insider. In his first mission, Gordon spies on a family-run Greek eatery that's gone downhill.</desc>
    <category lang="en">Entertainment</category>
    <category lang="en">Cooking</category>
    <language>en</language>
    <icon src="https://images.metadata.sky.com/pd-image/a9e12f52-34e3-4412-9eb6-a38f3f206d5a/16-9" />
  </programme><programme channel="Channel-4-UK" start="20260420045000 +0500" stop="20260420054000 +0500">
    <title>Gordon Ramsay's Secret Service</title>
    <sub-title>Caffe Boa</sub-title>
    <desc>Gordon Ramsay infiltrates struggling restaurants with the help of a secret insider. Can Gordon change owner Patrick's toxic ways to save his business - and his marriage.</desc>
    <category lang="en">Entertainment</category>
    <category lang="en">Cooking</category>
    <language>en</language>
    <icon src="https://images.metadata.sky.com/pd-image/bc44d7f0-49f4-4b99-a01c-521de03d5f6f/16-9" />
  </programme><programme channel="Channel-4-UK" start="20260420054000 +0500" stop="20260420063000 +0500">
    <title>Outrageous Homes</title>
    <sub-title />
    <desc>Laurence Llewelyn-Bowen checks out the UK's most unconventional and eclectic homes, including a barn that pays homage to Treasure Island and a magnificently mosaicked house.</desc>
    <category lang="en">Entertainment</category>
    <category lang="en">Home</category>
    <language>en</language>
    <icon src="https://images.metadata.sky.com/pd-image/f45107a9-8c23-3722-a428-2ce98a00c151/16-9" />
  </programme><programme channel="Channel-4-UK" start="20260420063000 +0500" stop="20260420072500 +0500">
    <title>George Clarke's Old House New Home</title>
    <sub-title />
    <desc>George is out and about with his sledgehammer, knocking holes in a fake Tudor ceiling in Leamington Spa and moving doors in a farmhouse on the edge of the Peak District.</desc>
    <category lang="en">Entertainment</category>
    <category lang="en">Lifestyles</category>
    <language>en</language>
    <icon src="https://images.metadata.sky.com/pd-image/d3ea3f39-bef0-4e71-a3c1-de714e5c689f/16-9" />
  </programme><programme channel="Channel-4-UK" start="20260420072500 +0500" stop="20260420081500 +0500">
    <title>Couples Come Dine with Me</title>
    <sub-title />
    <desc>In Manchester, three couples compete in a week featuring refined dining, strippergram revelations and awkward conversations about age differences.</desc>
    <category lang="en">Entertainment</category>
    <category lang="en">Cooking</category>
    <language>en</language>
    <icon src="https://images.metadata.sky.com/pd-image/1538c375-fa04-4003-b960-cc3d7c13fbd8/16-9" />
  </programme><programme channel="Channel-4-UK" start="20260420081500 +0500" stop="20260420083000 +0500">
    <title>Sunday Brunch</title>
    <sub-title />
    <desc>Some extra brunch as Tim Lovejoy and Simon Rimmer host the food and chat show.</desc>
    <category lang="en">Entertainment</category>
    <category lang="en">Magazine</category>
    <language>en</language>
    <icon src="https://images.metadata.sky.com/pd-image/6aceca02-8cc7-4d48-bcee-85ff5e739a25/16-9" />
  </programme><programme channel="Channel-4-UK" start="20260420083000 +0500" stop="20260420085500 +0500">
    <title>The Simpsons</title>
    <sub-title>The Saga of Carl</sub-title>
    <desc>Homer, Moe, Lenny and Carl win the lottery, but Carl runs off to Iceland with the winnings.</desc>
    <category lang="en">Entertainment</category>
    <category lang="en">Animation</category>
    <language>en</language>
    <icon src="https://images.metadata.sky.com/pd-image/9fd19c90-e29e-47fd-9794-135740469e97/16-9" />
  </programme><programme channel="Channel-4-UK" start="20260420085500 +0500" stop="20260420092000 +0500">
    <title>The Simpsons</title>
    <sub-title>Dangers on a Train</sub-title>
    <desc>While she's browsing for wedding anniversary cakes, Marge stumbles across a website for married people who want to have affairs.</desc>
    <category lang="en">Entertainment</category>
    <category lang="en">Animation</category>
    <language>en</language>
    <icon src="https://images.metadata.sky.com/pd-image/9e1bf6d4-ce2a-4a53-a4e5-759f39f4d85a/16-9" />
  </programme><programme channel="Channel-4-UK" start="20260420092000 +0500" stop="20260420094500 +0500">
    <title>The Simpsons</title>
    <sub-title>The Fabulous Faker Boy</sub-title>
    <desc>Bart doesn't want to go to piano lessons, until he meets his beautiful teacher... Homer loses the last two hairs on his head.</desc>
    <category lang="en">Entertainment</category>
    <category lang="en">Animation</category>
    <language>en</language>
    <icon src="https://images.metadata.sky.com/pd-image/ab670e40-76cf-4645-9d69-662f704f924a/16-9" />
  </programme><programme channel="Channel-4-UK" start="20260420094500 +0500" stop="20260420102500 +0500">
    <title>Countdown</title>
    <sub-title />
    <desc>Another chance to catch Friday's new episode, with Ranvir Singh in Dictionary Corner. Colin Murray, Rachel Riley and Susie Dent host.</desc>
    <category lang="en">Entertainment</category>
    <category lang="en">Game Show</category>
    <language>en</language>
    <icon src="https://images.metadata.sky.com/pd-image/8fcddeaa-56ad-4c1f-a532-34fdcba0e471/16-9" />
  </programme><programme channel="Channel-4-UK" start="20260420102500 +0500" stop="20260420105500 +0500">
    <title>Cheers</title>
    <sub-title>Diane Meets Mom</sub-title>
    <desc>A nervous Diane tries to create a good impression when she meets Frasier's mum Hester. But Hester gives Diane some dire warnings..</desc>
    <category lang="en">Entertainment</category>
    <category lang="en">Comedy</category>
    <language>en</language>
    <icon src="https://images.metadata.sky.com/pd-image/4ae26393-055a-42fa-8f68-9250e243ba78/16-9" />
  </programme><programme channel="Channel-4-UK" start="20260420105500 +0500" stop="20260420112000 +0500">
    <title>Cheers</title>
    <sub-title>An American Family</sub-title>
    <desc>Carla's ex-husband Nick returns with his new bride, demanding custody of their eldest son. And everyone's shocked when Carla agrees to the request.</desc>
    <category lang="en">Entertainment</category>
    <category lang="en">Comedy</category>
    <language>en</language>
    <icon src="https://images.metadata.sky.com/pd-image/b5d1ae74-8486-41c0-a495-10ac6425b9e4/16-9" />
  </programme><programme channel="Channel-4-UK" start="20260420112000 +0500" stop="20260420115000 +0500">
    <title>Cheers</title>
    <sub-title>Diane's Allergy</sub-title>
    <desc>After moving in with Frasier, Diane develops a chronic allergy that she thinks is caused by his dog. But is her reaction psychosomatic.</desc>
    <category lang="en">Entertainment</category>
    <category lang="en">Comedy</category>
    <language>en</language>
    <icon src="https://images.metadata.sky.com/pd-image/14aff548-49b5-4d23-b869-3f02ee3361dc/16-9" />
  </programme><programme channel="Channel-4-UK" start="20260420115000 +0500" stop="20260420121500 +0500">
    <title>Everybody Loves Raymond</title>
    <sub-title>Traffic School</sub-title>
    <desc>Robert's traffic school students are bored by his class, so he introduces Traffic Cop Timmy, a puppet who's anything but boring.</desc>
    <category lang="en">Entertainment</category>
    <category lang="en">Comedy</category>
    <language>en</language>
    <icon src="https://images.metadata.sky.com/pd-image/afa52242-3805-44e1-ace1-7f712177189d/16-9" />
  </programme><programme channel="Channel-4-UK" start="20260420121500 +0500" stop="20260420124000 +0500">
    <title>Everybody Loves Raymond</title>
    <sub-title>Six Feet Under</sub-title>
    <desc>Ray becomes concerned with his own mortality when he discovers that he's shrunk a quarter of an inch and is no longer six feet tall.</desc>
    <category lang="en">Entertainment</category>
    <category lang="en">Comedy</category>
    <language>en</language>
    <icon src="https://images.metadata.sky.com/pd-image/9c6b41e4-723f-488f-a995-343c50f2f73c/16-9" />
  </programme><programme channel="Channel-4-UK" start="20260420124000 +0500" stop="20260420131000 +0500">
    <title>Everybody Loves Raymond</title>
    <sub-title>The Garage Sale</sub-title>
    <desc>Ray's shocked when Debra takes all their baby stuff to a garage sale. He didn't know that they'd decided not to have any more children.</desc>
    <category lang="en">Entertainment</category>
    <category lang="en">Comedy</category>
    <language>en</language>
    <icon src="https://images.metadata.sky.com/pd-image/329e407d-93ba-4d8f-877d-f6d169d2e5b6/16-9" />
  </programme><programme channel="Channel-4-UK" start="20260420131000 +0500" stop="20260420134000 +0500">
    <title>Frasier</title>
    <sub-title>Door Jam</sub-title>
    <desc>Frasier and Niles enjoy the plush comforts of Seattle's premier spa and are happy with their pampering - until they discover there's a 'Gold Level'.</desc>
    <category lang="en">Entertainment</category>
    <category lang="en">Comedy</category>
    <language>en</language>
    <icon src="https://images.metadata.sky.com/pd-image/79b761c6-1be1-4aec-b397-ddc1d8241fb1/16-9" />
  </programme><programme channel="Channel-4-UK" start="20260420134000 +0500" stop="20260420141000 +0500">
    <title>Frasier</title>
    <sub-title>The Harassed</sub-title>
    <desc>Tension mounts when Frasier's forced to share his studio and airtime with the station's new finance reporter, an arrogant ex-stock market analyst.</desc>
    <category lang="en">Entertainment</category>
    <category lang="en">Comedy</category>
    <language>en</language>
    <icon src="https://images.metadata.sky.com/pd-image/443cf8f7-6e57-481c-ba13-324ccfedebc1/16-9" />
  </programme><programme channel="Channel-4-UK" start="20260420141000 +0500" stop="20260420144000 +0500">
    <title>Frasier</title>
    <sub-title>Lilith Needs a Favor</sub-title>
    <desc>Lilith pays an unexpected visit to Seattle and tells Frasier that she would like another child through artificial insemination.</desc>
    <category lang="en">Entertainment</category>
    <category lang="en">Comedy</category>
    <language>en</language>
    <icon src="https://images.metadata.sky.com/pd-image/4e2fdb3f-dec5-4336-b57b-9051289c0ac2/16-9" />
  </programme><programme channel="Channel-4-UK" start="20260420144000 +0500" stop="20260420151000 +0500">
    <title>Frasier</title>
    <sub-title>Daphne Does Dinner</sub-title>
    <desc>Niles plans a very special dinner party to mark the purchase of a new painting he's bought for Daphne. But catastrophe ensues.</desc>
    <category lang="en">Entertainment</category>
    <category lang="en">Comedy</category>
    <language>en</language>
    <icon src="https://images.metadata.sky.com/pd-image/26da4e66-852e-4542-96da-d9cee0713c16/16-9" />
  </programme><programme channel="Channel-4-UK" start="20260420151000 +0500" stop="20260420160500 +0500">
    <title>Ramsay's Kitchen Nightmares USA</title>
    <sub-title>Bel Aire</sub-title>
    <desc>Can Gordon Ramsay get two brothers to work through their problems and save their failing New York diner.</desc>
    <category lang="en">Entertainment</category>
    <category lang="en">Cooking</category>
    <language>en</language>
    <icon src="https://images.metadata.sky.com/pd-image/f88e518a-999e-3ba8-ad7b-b68ff1b05c89/16-9" />
  </programme><programme channel="Channel-4-UK" start="20260420160500 +0500" stop="20260420161000 +0500">
    <title>Channel 4 News Summary</title>
    <sub-title />
    <desc>Channel 4's midday news summary.</desc>
    <category lang="en">News &amp; Documentary</category>
    <category lang="en">News</category>
    <language>en</language>
    <icon src="https://images.metadata.sky.com/pd-image/e1c9d995-0fc3-40ac-bf61-f8aa02aa11e1/16-9" />
  </programme><programme channel="Channel-4-UK" start="20260420161000 +0500" stop="20260420171000 +0500">
    <title>Find It, Fix It, Flog It</title>
    <sub-title />
    <desc>In Birmingham, Henry Cole stumbles upon a model metal tipper truck which he's convinced will make money.</desc>
    <category lang="en">Entertainment</category>
    <category lang="en">Factual</category>
    <language>en</language>
    <icon src="https://images.metadata.sky.com/pd-image/b315be0b-a520-4cef-b4bb-1154fb018c57/16-9" />
  </programme><programme channel="Channel-4-UK" start="20260420171000 +0500" stop="20260420181000 +0500">
    <title>Matt Baker: Travels with Mum &amp; Dad</title>
    <sub-title />
    <desc>The Bakers bring Bowes Museum's marvellous mechanical swan back to life, and relive fond family memories at High Force waterfall.</desc>
    <category lang="en">Entertainment</category>
    <category lang="en">Lifestyles</category>
    <language>en</language>
    <icon src="https://images.metadata.sky.com/pd-image/f5022ac9-2f19-3b07-a6b5-2bd6ee14fc98/16-9" />
  </programme><programme channel="Channel-4-UK" start="20260420181000 +0500" stop="20260420190000 +0500">
    <title>Countdown</title>
    <sub-title />
    <desc>Colin Murray, Rachel Riley and Susie Dent host, with Richard Whitehead in Dictionary Corner, as contestants race against the clock to pit their wits against vowels, consonants and numbers.</desc>
    <category lang="en">Entertainment</category>
    <category lang="en">Game Show</category>
    <language>en</language>
    <icon src="https://images.metadata.sky.com/pd-image/7b3f075b-3c76-4624-97ea-0aa444afd75b/16-9" />
  </programme><programme channel="Channel-4-UK" start="20260420190000 +0500" stop="20260420200000 +0500">
    <title>A Place in the Sun</title>
    <sub-title />
    <desc>Carpenter David from Suffolk wants an apartment near the beach in Abruzzo on Italy's east coast. Craig Rowe shows him what his £45,000 can buy.</desc>
    <category lang="en">Entertainment</category>
    <category lang="en">Lifestyles</category>
    <language>en</language>
    <icon src="https://images.metadata.sky.com/pd-image/842c18be-e0a5-417c-8714-d9667bc33f4d/16-9" />
  </programme><programme channel="Channel-4-UK" start="20260420200000 +0500" stop="20260420210000 +0500">
    <title>A New Life in the Sun: Where Are They Now?</title>
    <sub-title />
    <desc>Gîte owners Mark and Lesley take flight with a new idea over a Normandy beach. Fitness instructor Ali sets sail on a new adventure.</desc>
    <category lang="en">Entertainment</category>
    <category lang="en">Travel</category>
    <language>en</language>
    <icon src="https://images.metadata.sky.com/pd-image/3e1f9662-6e31-30fe-9b17-79aa0abf3ffd/16-9" />
  </programme><programme channel="Channel-4-UK" start="20260420210000 +0500" stop="20260420220000 +0500">
    <title>Chateau DIY</title>
    <sub-title>The new series continues</sub-title>
    <desc>Erin and JB race to light up their salon. Anna and Edward rebuild their lake's sweeping stairway. Christina and Sassan transform their grand front gates.</desc>
    <category lang="en">Entertainment</category>
    <category lang="en">Home</category>
    <language>en</language>
    <icon src="https://images.metadata.sky.com/pd-image/8cfa2a27-6db0-4e17-a850-d2524b4cbfe3/16-9" />
  </programme><programme channel="Channel-4-UK" start="20260420220000 +0500" stop="20260420230000 +0500">
    <title>Sun, Sea and Selling Houses</title>
    <sub-title />
    <desc>A new series with our favourite family-run estate agents. In Almería, the Garners juggle wow-factor villas and a wildcard. Lisa and John face tough compromises on the Costa Blanca.</desc>
    <category lang="en">Entertainment</category>
    <category lang="en">Lifestyles</category>
    <language>en</language>
    <icon src="https://images.metadata.sky.com/pd-image/256cd5ee-f3cf-4baf-a6e9-962606025cae/16-9" />
  </programme><programme channel="Channel-4-UK" start="20260420230000 +0500" stop="20260421000000 +0500">
    <title>Channel 4 News</title>
    <sub-title />
    <desc>Channel 4's flagship news programme. Including the weather.</desc>
    <category lang="en">News &amp; Documentary</category>
    <category lang="en">News</category>
    <language>en</language>
    <icon src="https://images.metadata.sky.com/pd-image/8efa4bd3-2a13-4624-91c9-9d315c5f7c34/16-9" />
  </programme>
</tv>