<?xml version='1.0' encoding='utf-8'?>
<tv>
  <channel id="FYI-East-US">
    <display-name>FYI East</display-name>
    <icon src="https://thefilmtuition.com/tvlogo/FYI-East-US.png" />
  </channel><programme channel="FYI-East-US" start="20260416000000 +0500" stop="20260416003000 +0500">
    <title>Oceanfront Property Hunt</title>
    <sub-title>Elizabeth and Ryan</sub-title>
    <desc>For sea lovers Elizabeth and Ryan, any day spent on the water is a wonderful day; after experiencing a health scare, they realize it is time to pursue their passions full-time.</desc>
    <episode-num system="onscreen">S1 E10</episode-num>
    <date>2025</date>
    <category lang="en">Series</category>
    <category lang="en">Home improvement</category>
    <language>en</language>
    <icon src="http://dtil.tmsimg.com/assets/p29074335_b_h8_ab.jpg?w=960&amp;h=540" />
  </programme><programme channel="FYI-East-US" start="20260416003000 +0500" stop="20260416010000 +0500">
    <title>Oceanfront Property Hunt</title>
    <sub-title>Naana and Daren</sub-title>
    <desc>Daren and Naana are searching for a turn-key home with an ocean view; they need a location to open their dream roadside ice cream shop.</desc>
    <episode-num system="onscreen">S1 E8</episode-num>
    <date>2025</date>
    <category lang="en">Series</category>
    <category lang="en">Home improvement</category>
    <language>en</language>
    <icon src="http://dtil.tmsimg.com/assets/p29074335_b_h8_ab.jpg?w=960&amp;h=540" />
  </programme><programme channel="FYI-East-US" start="20260416010000 +0500" stop="20260416013000 +0500">
    <title>Lakefront Luxury</title>
    <sub-title>Frankie &amp; Jacques</sub-title>
    <desc>Frankie and Jacques love entertaining friends and family for game nights; they are looking for a home on the water, where they can jump off a dock and into the lake after a competitive game or two.</desc>
    <episode-num system="onscreen">S5 E10</episode-num>
    <credits>
      <director>Michael Gelman</director>
    </credits><date>2025</date>
    <category lang="en">Series</category>
    <category lang="en">Reality</category>
    <category lang="en">House/garden</category>
    <language>en</language>
    <icon src="http://dtil.tmsimg.com/assets/p15200923_b_h8_aq.jpg?w=960&amp;h=540" />
    <rating system="Australian Classification Board">
      <value>PG</value>
    </rating><rating system="Canadian Parental Rating">
      <value>PG</value>
    </rating><rating system="USA Parental Rating">
      <value>TVPG</value>
    </rating><rating system="Kijkwijzer">
      <value>12</value>
    </rating>
  </programme><programme channel="FYI-East-US" start="20260416013000 +0500" stop="20260416020000 +0500">
    <title>Lakefront Luxury</title>
    <sub-title>Derek &amp; Joanne</sub-title>
    <desc>Derek and Joanne are looking to move from a golf course to a waterfront property; their house search takes them to various properties; the first one that is built into a huge boulder and the second that's build on top of natural granite.</desc>
    <episode-num system="onscreen">S5 E11</episode-num>
    <credits>
      <director>Michael Gelman</director>
    </credits><date>2025</date>
    <category lang="en">Series</category>
    <category lang="en">Reality</category>
    <category lang="en">House/garden</category>
    <language>en</language>
    <icon src="http://dtil.tmsimg.com/assets/p15200923_b_h8_aq.jpg?w=960&amp;h=540" />
    <rating system="Australian Classification Board">
      <value>PG</value>
    </rating><rating system="Canadian Parental Rating">
      <value>PG</value>
    </rating><rating system="USA Parental Rating">
      <value>TVPG</value>
    </rating><rating system="Kijkwijzer">
      <value>12</value>
    </rating>
  </programme><programme channel="FYI-East-US" start="20260416020000 +0500" stop="20260416023000 +0500">
    <title>Lakefront Luxury</title>
    <sub-title>Calvin &amp; Justin</sub-title>
    <desc>Calvin and Justin love the water and even own a boat, but they don't yet own a lakefront home where they can park it; their property search takes them to an entertainer's dream home, which is a resort-like retreat with two separate living spaces.</desc>
    <episode-num system="onscreen">S5 E12</episode-num>
    <credits>
      <director>Michael Gelman</director>
    </credits><date>2025</date>
    <category lang="en">Series</category>
    <category lang="en">Reality</category>
    <category lang="en">House/garden</category>
    <language>en</language>
    <icon src="http://dtil.tmsimg.com/assets/p26975061_b_h8_ab.jpg?w=960&amp;h=540" />
    <rating system="Australian Classification Board">
      <value>PG</value>
    </rating><rating system="Canadian Parental Rating">
      <value>PG</value>
    </rating><rating system="USA Parental Rating">
      <value>TVPG</value>
    </rating><rating system="Kijkwijzer">
      <value>12</value>
    </rating>
  </programme><programme channel="FYI-East-US" start="20260416023000 +0500" stop="20260416030000 +0500">
    <title>Lakefront Luxury</title>
    <sub-title>David &amp; Maxine</sub-title>
    <desc>Dave and Maxine want a spacious lakefront retreat for their family; they tour a modern-rustic home with concrete floors, a nautical-inspired riverfront escape, and a sleek rustic build with a sunken living room and stunning lake views.</desc>
    <episode-num system="onscreen">S5 E13</episode-num>
    <date>2025</date>
    <category lang="en">Series</category>
    <category lang="en">Reality</category>
    <category lang="en">House/garden</category>
    <language>en</language>
    <icon src="http://dtil.tmsimg.com/assets/p26975061_b_h8_ab.jpg?w=960&amp;h=540" />
    <rating system="Australian Classification Board">
      <value>PG</value>
    </rating><rating system="Canadian Parental Rating">
      <value>PG</value>
    </rating><rating system="USA Parental Rating">
      <value>TVPG</value>
    </rating><rating system="Kijkwijzer">
      <value>12</value>
    </rating>
  </programme><programme channel="FYI-East-US" start="20260416030000 +0500" stop="20260416033000 +0500">
    <title>Lakefront Luxury</title>
    <sub-title>Tina &amp; Tony</sub-title>
    <desc>Tina and Tony are searching for the perfect lakefront estate to host their large Italian family; they visit a stunning entertainer's paradise, a sprawling 4,300 sq. ft. home with an amazing outdoor living space, and a sleek, modern canal-side home.</desc>
    <episode-num system="onscreen">S5 E14</episode-num>
    <date>2025</date>
    <category lang="en">Series</category>
    <category lang="en">Reality</category>
    <category lang="en">House/garden</category>
    <language>en</language>
    <icon src="http://dtil.tmsimg.com/assets/p15200923_b_h8_aq.jpg?w=960&amp;h=540" />
    <rating system="Australian Classification Board">
      <value>PG</value>
    </rating><rating system="Canadian Parental Rating">
      <value>PG</value>
    </rating><rating system="USA Parental Rating">
      <value>TVPG</value>
    </rating><rating system="Kijkwijzer">
      <value>12</value>
    </rating>
  </programme><programme channel="FYI-East-US" start="20260416033000 +0500" stop="20260416040000 +0500">
    <title>Lakefront Luxury</title>
    <sub-title>Basil &amp; Belinda</sub-title>
    <desc>Musicians Basil and Belinda seek the perfect lakefront party house; they explore a rustic 6-bedroom retreat with a private beach, a 4-bedroom stunner with a saltwater pool and rooftop deck, and a sleek modern home with a spa-like ensuite and sandy shoreline; which home will hit the right note?</desc>
    <episode-num system="onscreen">S5 E15</episode-num>
    <date>2025</date>
    <category lang="en">Series</category>
    <category lang="en">Reality</category>
    <category lang="en">House/garden</category>
    <language>en</language>
    <icon src="http://dtil.tmsimg.com/assets/p15200923_b_h8_aq.jpg?w=960&amp;h=540" />
    <rating system="Australian Classification Board">
      <value>PG</value>
    </rating><rating system="Canadian Parental Rating">
      <value>PG</value>
    </rating><rating system="USA Parental Rating">
      <value>TVPG</value>
    </rating><rating system="Kijkwijzer">
      <value>12</value>
    </rating>
  </programme><programme channel="FYI-East-US" start="20260416040000 +0500" stop="20260416043000 +0500">
    <title>Lakefront Luxury</title>
    <sub-title>Alex &amp; Cheryl</sub-title>
    <desc>Empty nesters Alex and Cheryl are searching for their forever lakefront home. Options include a 13-acre estate with a private beach, a traditionally styled retreat with a wine cellar and European-inspired outdoor spaces, and a modern escape with seamless indoor-outdoor living. Which dream home will they choose?</desc>
    <episode-num system="onscreen">S5 E16</episode-num>
    <date>2025</date>
    <category lang="en">Series</category>
    <category lang="en">Reality</category>
    <category lang="en">House/garden</category>
    <language>en</language>
    <icon src="http://dtil.tmsimg.com/assets/p26975061_b_h8_ab.jpg?w=960&amp;h=540" />
    <rating system="Australian Classification Board">
      <value>PG</value>
    </rating><rating system="Canadian Parental Rating">
      <value>PG</value>
    </rating><rating system="USA Parental Rating">
      <value>TVPG</value>
    </rating><rating system="Kijkwijzer">
      <value>12</value>
    </rating>
  </programme><programme channel="FYI-East-US" start="20260416043000 +0500" stop="20260416050000 +0500">
    <title>Lakefront Luxury</title>
    <sub-title>Alain &amp; Sara</sub-title>
    <desc>Sustainable farmers Alain and Sara want a lakefront home that fits their eco-friendly lifestyle; they tour a Florida-style bungalow ideal for beekeeping, a traditional home with a private lake and farm space, and a modern retreat.</desc>
    <episode-num system="onscreen">S5 E17</episode-num>
    <date>2025</date>
    <category lang="en">Series</category>
    <category lang="en">Reality</category>
    <category lang="en">House/garden</category>
    <language>en</language>
    <icon src="http://dtil.tmsimg.com/assets/p26975061_b_h8_ab.jpg?w=960&amp;h=540" />
    <rating system="Australian Classification Board">
      <value>PG</value>
    </rating><rating system="Canadian Parental Rating">
      <value>PG</value>
    </rating><rating system="USA Parental Rating">
      <value>TVPG</value>
    </rating><rating system="Kijkwijzer">
      <value>12</value>
    </rating>
  </programme><programme channel="FYI-East-US" start="20260416050000 +0500" stop="20260416053000 +0500">
    <title>Lakefront Luxury</title>
    <sub-title>Julia &amp; Matteo</sub-title>
    <desc>Julia and Matteo want a vacation home with a top-tier kitchen for Italian feasts and space for classic cars; they tour a Mediterranean-inspired retreat with a waterfront kitchen, a nautical-themed escape with a loft and bar, and a sleek, modern build with forest views; which home will they choose?</desc>
    <episode-num system="onscreen">S5 E18</episode-num>
    <date>2025</date>
    <category lang="en">Series</category>
    <category lang="en">Reality</category>
    <category lang="en">House/garden</category>
    <language>en</language>
    <icon src="http://dtil.tmsimg.com/assets/p26975061_b_h8_ab.jpg?w=960&amp;h=540" />
    <rating system="Australian Classification Board">
      <value>PG</value>
    </rating><rating system="Canadian Parental Rating">
      <value>PG</value>
    </rating><rating system="USA Parental Rating">
      <value>TVPG</value>
    </rating><rating system="Kijkwijzer">
      <value>12</value>
    </rating>
  </programme><programme channel="FYI-East-US" start="20260416053000 +0500" stop="20260416060000 +0500">
    <title>Lakefront Luxury</title>
    <sub-title>Jessica &amp; Zach</sub-title>
    <desc>Jessica and Zack are ready to trade their beachfront home for a lakefront dream; they explore an 8,000-square-foot French-inspired estate, a 7,000-square-foot home with an ice rink, and a charming, elegant retreat with a sandy beach.</desc>
    <episode-num system="onscreen">S5 E19</episode-num>
    <date>2025</date>
    <category lang="en">Series</category>
    <category lang="en">Reality</category>
    <category lang="en">House/garden</category>
    <language>en</language>
    <icon src="http://dtil.tmsimg.com/assets/p26975061_b_h8_ab.jpg?w=960&amp;h=540" />
    <rating system="Australian Classification Board">
      <value>PG</value>
    </rating><rating system="Canadian Parental Rating">
      <value>PG</value>
    </rating><rating system="USA Parental Rating">
      <value>TVPG</value>
    </rating><rating system="Kijkwijzer">
      <value>12</value>
    </rating>
  </programme><programme channel="FYI-East-US" start="20260416060000 +0500" stop="20260416063000 +0500">
    <title>Lakefront Luxury</title>
    <sub-title>Eric &amp; Lisa</sub-title>
    <desc>Eric and Lisa are ready to turn their vision board into reality with a dream lakefront property; from ultra-modern luxury to rustic charm, their options promise sweeping views, show-stopping kitchens, and stunning outdoor features.</desc>
    <episode-num system="onscreen">S5 E20</episode-num>
    <date>2025</date>
    <category lang="en">Series</category>
    <category lang="en">Reality</category>
    <category lang="en">House/garden</category>
    <language>en</language>
    <icon src="http://dtil.tmsimg.com/assets/p26975061_b_h8_ab.jpg?w=960&amp;h=540" />
    <rating system="Australian Classification Board">
      <value>PG</value>
    </rating><rating system="Canadian Parental Rating">
      <value>PG</value>
    </rating><rating system="USA Parental Rating">
      <value>TVPG</value>
    </rating><rating system="Kijkwijzer">
      <value>12</value>
    </rating>
  </programme><programme channel="FYI-East-US" start="20260416063000 +0500" stop="20260416070000 +0500">
    <title>Lakefront Luxury</title>
    <sub-title>Andrea &amp; Ted</sub-title>
    <desc>Andrea and Ted are trading mountain views for lakeside living as they search for the perfect home for their growing family; from sleek modern architecture to charming traditional retreats, the possibilities are as varied as their vision; which dream home will win their hearts?</desc>
    <episode-num system="onscreen">S5 E21</episode-num>
    <date>2026</date>
    <category lang="en">Series</category>
    <category lang="en">Reality</category>
    <category lang="en">House/garden</category>
    <language>en</language>
    <icon src="http://dtil.tmsimg.com/assets/p15200923_b_h8_aq.jpg?w=960&amp;h=540" />
    <rating system="Australian Classification Board">
      <value>PG</value>
    </rating><rating system="Canadian Parental Rating">
      <value>PG</value>
    </rating><rating system="USA Parental Rating">
      <value>TVPG</value>
    </rating><rating system="Kijkwijzer">
      <value>12</value>
    </rating>
  </programme><programme channel="FYI-East-US" start="20260416070000 +0500" stop="20260416073000 +0500">
    <title>Lakefront Luxury</title>
    <sub-title>Jason &amp; Michael</sub-title>
    <desc>Jason and Michael are trading in two homes for one dream lakefront estate; with their dogs and future entertaining in mind, they tour three spectacular properties featuring gourmet kitchens, stunning great rooms, and incredible outdoor spaces; which lakeside retreat will become their forever home?</desc>
    <episode-num system="onscreen">S5 E22</episode-num>
    <date>2026</date>
    <category lang="en">Series</category>
    <category lang="en">Reality</category>
    <category lang="en">House/garden</category>
    <language>en</language>
    <icon src="http://dtil.tmsimg.com/assets/p15200923_b_h8_aq.jpg?w=960&amp;h=540" />
    <rating system="Australian Classification Board">
      <value>PG</value>
    </rating><rating system="Canadian Parental Rating">
      <value>PG</value>
    </rating><rating system="USA Parental Rating">
      <value>TVPG</value>
    </rating><rating system="Kijkwijzer">
      <value>12</value>
    </rating>
  </programme><programme channel="FYI-East-US" start="20260416073000 +0500" stop="20260416080100 +0500">
    <title>Lakefront Luxury</title>
    <sub-title>Antoinette &amp; Levin</sub-title>
    <desc>Newlyweds Antoinette and Levin are seeking a stunning lakefront property to become their family's forever home. Will it be modern luxury, vintage charm, or timeless elegance that wins their hearts?</desc>
    <episode-num system="onscreen">S5 E23</episode-num>
    <date>2026</date>
    <category lang="en">Series</category>
    <category lang="en">Reality</category>
    <category lang="en">House/garden</category>
    <language>en</language>
    <icon src="http://dtil.tmsimg.com/assets/p26975061_b_h8_ab.jpg?w=960&amp;h=540" />
    <rating system="Australian Classification Board">
      <value>PG</value>
    </rating><rating system="Canadian Parental Rating">
      <value>PG</value>
    </rating><rating system="USA Parental Rating">
      <value>TVPG</value>
    </rating><rating system="Kijkwijzer">
      <value>12</value>
    </rating>
  </programme><programme channel="FYI-East-US" start="20260416080100 +0500" stop="20260416083100 +0500">
    <title>Lakefront Luxury</title>
    <sub-title>Asim &amp; Sheila</sub-title>
    <desc>Retired boat-dwellers Asim and Sheila are ready to anchor down on land; as they tour elegant homes with stunning kitchens, timber ceilings, and waterfront decks, they're searching for the perfect place to settle; which lakefront gem will win their hearts?</desc>
    <episode-num system="onscreen">S5 E24</episode-num>
    <date>2026</date>
    <category lang="en">Series</category>
    <category lang="en">Reality</category>
    <category lang="en">House/garden</category>
    <language>en</language>
    <icon src="http://dtil.tmsimg.com/assets/p15200923_b_h8_aq.jpg?w=960&amp;h=540" />
    <rating system="Australian Classification Board">
      <value>PG</value>
    </rating><rating system="Canadian Parental Rating">
      <value>PG</value>
    </rating><rating system="USA Parental Rating">
      <value>TVPG</value>
    </rating><rating system="Kijkwijzer">
      <value>12</value>
    </rating>
  </programme><programme channel="FYI-East-US" start="20260416083100 +0500" stop="20260416090000 +0500">
    <title>Lakefront Luxury</title>
    <sub-title>Tage &amp; Vivian</sub-title>
    <desc>Tage and Vivian are seeking a spacious lakefront haven for their growing family; touring elegant properties with gourmet kitchens, grand fireplaces, and lush outdoor terraces, they're ready to pick their perfect retirement retreat.</desc>
    <episode-num system="onscreen">S5 E25</episode-num>
    <date>2026</date>
    <category lang="en">Series</category>
    <category lang="en">Reality</category>
    <category lang="en">House/garden</category>
    <language>en</language>
    <icon src="http://dtil.tmsimg.com/assets/p26975061_b_h8_ab.jpg?w=960&amp;h=540" />
    <rating system="Australian Classification Board">
      <value>PG</value>
    </rating><rating system="Canadian Parental Rating">
      <value>PG</value>
    </rating><rating system="USA Parental Rating">
      <value>TVPG</value>
    </rating><rating system="Kijkwijzer">
      <value>12</value>
    </rating>
  </programme><programme channel="FYI-East-US" start="20260416090000 +0500" stop="20260416093000 +0500">
    <title>Lakefront Luxury</title>
    <sub-title>Julia &amp; Matteo</sub-title>
    <desc>Julia and Matteo want a vacation home with a top-tier kitchen for Italian feasts and space for classic cars; they tour a Mediterranean-inspired retreat with a waterfront kitchen, a nautical-themed escape with a loft and bar, and a sleek, modern build with forest views; which home will they choose?</desc>
    <episode-num system="onscreen">S5 E18</episode-num>
    <date>2025</date>
    <category lang="en">Series</category>
    <category lang="en">Reality</category>
    <category lang="en">House/garden</category>
    <language>en</language>
    <icon src="http://dtil.tmsimg.com/assets/p26975061_b_h8_ab.jpg?w=960&amp;h=540" />
    <rating system="Australian Classification Board">
      <value>PG</value>
    </rating><rating system="Canadian Parental Rating">
      <value>PG</value>
    </rating><rating system="USA Parental Rating">
      <value>TVPG</value>
    </rating><rating system="Kijkwijzer">
      <value>12</value>
    </rating>
  </programme><programme channel="FYI-East-US" start="20260416093000 +0500" stop="20260416100000 +0500">
    <title>Lakefront Luxury</title>
    <sub-title>Jessica &amp; Zach</sub-title>
    <desc>Jessica and Zack are ready to trade their beachfront home for a lakefront dream; they explore an 8,000-square-foot French-inspired estate, a 7,000-square-foot home with an ice rink, and a charming, elegant retreat with a sandy beach.</desc>
    <episode-num system="onscreen">S5 E19</episode-num>
    <date>2025</date>
    <category lang="en">Series</category>
    <category lang="en">Reality</category>
    <category lang="en">House/garden</category>
    <language>en</language>
    <icon src="http://dtil.tmsimg.com/assets/p26975061_b_h8_ab.jpg?w=960&amp;h=540" />
    <rating system="Australian Classification Board">
      <value>PG</value>
    </rating><rating system="Canadian Parental Rating">
      <value>PG</value>
    </rating><rating system="USA Parental Rating">
      <value>TVPG</value>
    </rating><rating system="Kijkwijzer">
      <value>12</value>
    </rating>
  </programme><programme channel="FYI-East-US" start="20260416100000 +0500" stop="20260416103000 +0500">
    <title>Lakefront Luxury</title>
    <sub-title>Eric &amp; Lisa</sub-title>
    <desc>Eric and Lisa are ready to turn their vision board into reality with a dream lakefront property; from ultra-modern luxury to rustic charm, their options promise sweeping views, show-stopping kitchens, and stunning outdoor features.</desc>
    <episode-num system="onscreen">S5 E20</episode-num>
    <date>2025</date>
    <category lang="en">Series</category>
    <category lang="en">Reality</category>
    <category lang="en">House/garden</category>
    <language>en</language>
    <icon src="http://dtil.tmsimg.com/assets/p26975061_b_h8_ab.jpg?w=960&amp;h=540" />
    <rating system="Australian Classification Board">
      <value>PG</value>
    </rating><rating system="Canadian Parental Rating">
      <value>PG</value>
    </rating><rating system="USA Parental Rating">
      <value>TVPG</value>
    </rating><rating system="Kijkwijzer">
      <value>12</value>
    </rating>
  </programme><programme channel="FYI-East-US" start="20260416103000 +0500" stop="20260416110000 +0500">
    <title>Lakefront Luxury</title>
    <sub-title>Andrea &amp; Ted</sub-title>
    <desc>Andrea and Ted are trading mountain views for lakeside living as they search for the perfect home for their growing family; from sleek modern architecture to charming traditional retreats, the possibilities are as varied as their vision; which dream home will win their hearts?</desc>
    <episode-num system="onscreen">S5 E21</episode-num>
    <date>2026</date>
    <category lang="en">Series</category>
    <category lang="en">Reality</category>
    <category lang="en">House/garden</category>
    <language>en</language>
    <icon src="http://dtil.tmsimg.com/assets/p15200923_b_h8_aq.jpg?w=960&amp;h=540" />
    <rating system="Australian Classification Board">
      <value>PG</value>
    </rating><rating system="Canadian Parental Rating">
      <value>PG</value>
    </rating><rating system="USA Parental Rating">
      <value>TVPG</value>
    </rating><rating system="Kijkwijzer">
      <value>12</value>
    </rating>
  </programme><programme channel="FYI-East-US" start="20260416110000 +0500" stop="20260416113000 +0500">
    <title>Lakefront Luxury</title>
    <sub-title>Jason &amp; Michael</sub-title>
    <desc>Jason and Michael are trading in two homes for one dream lakefront estate; with their dogs and future entertaining in mind, they tour three spectacular properties featuring gourmet kitchens, stunning great rooms, and incredible outdoor spaces; which lakeside retreat will become their forever home?</desc>
    <episode-num system="onscreen">S5 E22</episode-num>
    <date>2026</date>
    <category lang="en">Series</category>
    <category lang="en">Reality</category>
    <category lang="en">House/garden</category>
    <language>en</language>
    <icon src="http://dtil.tmsimg.com/assets/p15200923_b_h8_aq.jpg?w=960&amp;h=540" />
    <rating system="Australian Classification Board">
      <value>PG</value>
    </rating><rating system="Canadian Parental Rating">
      <value>PG</value>
    </rating><rating system="USA Parental Rating">
      <value>TVPG</value>
    </rating><rating system="Kijkwijzer">
      <value>12</value>
    </rating>
  </programme><programme channel="FYI-East-US" start="20260416113000 +0500" stop="20260416120100 +0500">
    <title>Lakefront Luxury</title>
    <sub-title>Antoinette &amp; Levin</sub-title>
    <desc>Newlyweds Antoinette and Levin are seeking a stunning lakefront property to become their family's forever home. Will it be modern luxury, vintage charm, or timeless elegance that wins their hearts?</desc>
    <episode-num system="onscreen">S5 E23</episode-num>
    <date>2026</date>
    <category lang="en">Series</category>
    <category lang="en">Reality</category>
    <category lang="en">House/garden</category>
    <language>en</language>
    <icon src="http://dtil.tmsimg.com/assets/p26975061_b_h8_ab.jpg?w=960&amp;h=540" />
    <rating system="Australian Classification Board">
      <value>PG</value>
    </rating><rating system="Canadian Parental Rating">
      <value>PG</value>
    </rating><rating system="USA Parental Rating">
      <value>TVPG</value>
    </rating><rating system="Kijkwijzer">
      <value>12</value>
    </rating>
  </programme><programme channel="FYI-East-US" start="20260416120100 +0500" stop="20260416123100 +0500">
    <title>Lakefront Luxury</title>
    <sub-title>Asim &amp; Sheila</sub-title>
    <desc>Retired boat-dwellers Asim and Sheila are ready to anchor down on land; as they tour elegant homes with stunning kitchens, timber ceilings, and waterfront decks, they're searching for the perfect place to settle; which lakefront gem will win their hearts?</desc>
    <episode-num system="onscreen">S5 E24</episode-num>
    <date>2026</date>
    <category lang="en">Series</category>
    <category lang="en">Reality</category>
    <category lang="en">House/garden</category>
    <language>en</language>
    <icon src="http://dtil.tmsimg.com/assets/p15200923_b_h8_aq.jpg?w=960&amp;h=540" />
    <rating system="Australian Classification Board">
      <value>PG</value>
    </rating><rating system="Canadian Parental Rating">
      <value>PG</value>
    </rating><rating system="USA Parental Rating">
      <value>TVPG</value>
    </rating><rating system="Kijkwijzer">
      <value>12</value>
    </rating>
  </programme><programme channel="FYI-East-US" start="20260416123100 +0500" stop="20260416130000 +0500">
    <title>Lakefront Luxury</title>
    <sub-title>Tage &amp; Vivian</sub-title>
    <desc>Tage and Vivian are seeking a spacious lakefront haven for their growing family; touring elegant properties with gourmet kitchens, grand fireplaces, and lush outdoor terraces, they're ready to pick their perfect retirement retreat.</desc>
    <episode-num system="onscreen">S5 E25</episode-num>
    <date>2026</date>
    <category lang="en">Series</category>
    <category lang="en">Reality</category>
    <category lang="en">House/garden</category>
    <language>en</language>
    <icon src="http://dtil.tmsimg.com/assets/p26975061_b_h8_ab.jpg?w=960&amp;h=540" />
    <rating system="Australian Classification Board">
      <value>PG</value>
    </rating><rating system="Canadian Parental Rating">
      <value>PG</value>
    </rating><rating system="USA Parental Rating">
      <value>TVPG</value>
    </rating><rating system="Kijkwijzer">
      <value>12</value>
    </rating>
  </programme><programme channel="FYI-East-US" start="20260416130000 +0500" stop="20260416133000 +0500">
    <title>Lakefront Luxury</title>
    <sub-title>Frankie &amp; Jacques</sub-title>
    <desc>Frankie and Jacques love entertaining friends and family for game nights; they are looking for a home on the water, where they can jump off a dock and into the lake after a competitive game or two.</desc>
    <episode-num system="onscreen">S5 E10</episode-num>
    <credits>
      <director>Michael Gelman</director>
    </credits><date>2025</date>
    <category lang="en">Series</category>
    <category lang="en">Reality</category>
    <category lang="en">House/garden</category>
    <language>en</language>
    <icon src="http://dtil.tmsimg.com/assets/p15200923_b_h8_aq.jpg?w=960&amp;h=540" />
    <rating system="Australian Classification Board">
      <value>PG</value>
    </rating><rating system="Canadian Parental Rating">
      <value>PG</value>
    </rating><rating system="USA Parental Rating">
      <value>TVPG</value>
    </rating><rating system="Kijkwijzer">
      <value>12</value>
    </rating>
  </programme><programme channel="FYI-East-US" start="20260416133000 +0500" stop="20260416140000 +0500">
    <title>Lakefront Luxury</title>
    <sub-title>Derek &amp; Joanne</sub-title>
    <desc>Derek and Joanne are looking to move from a golf course to a waterfront property; their house search takes them to various properties; the first one that is built into a huge boulder and the second that's build on top of natural granite.</desc>
    <episode-num system="onscreen">S5 E11</episode-num>
    <credits>
      <director>Michael Gelman</director>
    </credits><date>2025</date>
    <category lang="en">Series</category>
    <category lang="en">Reality</category>
    <category lang="en">House/garden</category>
    <language>en</language>
    <icon src="http://dtil.tmsimg.com/assets/p15200923_b_h8_aq.jpg?w=960&amp;h=540" />
    <rating system="Australian Classification Board">
      <value>PG</value>
    </rating><rating system="Canadian Parental Rating">
      <value>PG</value>
    </rating><rating system="USA Parental Rating">
      <value>TVPG</value>
    </rating><rating system="Kijkwijzer">
      <value>12</value>
    </rating>
  </programme><programme channel="FYI-East-US" start="20260416140000 +0500" stop="20260416143000 +0500">
    <title>Inogen Portable Oxygen - No More Tanks!</title>
    <sub-title />
    <desc>Regain independence and enjoy greater mobility with the compact design and long-lasting battery of portable oxygen.</desc>
    <category lang="en">Health</category>
    <category lang="en">Consumer</category>
    <category lang="en">Science</category>
    <category lang="en">Medical</category>
    <category lang="en">Technology</category>
    <language>en</language>
    <icon src="http://dtil.tmsimg.com/assets/p17108681_b_h11_ab.jpg?w=960&amp;h=540" />
  </programme><programme channel="FYI-East-US" start="20260416143000 +0500" stop="20260416150000 +0500">
    <title>Paid Programming</title>
    <sub-title />
    <desc>Paid programming.</desc>
    <category lang="en">Consumer</category>
    <category lang="en">Shopping</category>
    <category lang="en">Variety</category>
    <language>en</language>
    <icon src="http://dtil.tmsimg.com/assets/p459763_b_h8_bq.jpg?w=960&amp;h=540" />
    <rating system="USA Parental Rating">
      <value>TVG</value>
    </rating><rating system="Régie du cinéma">
      <value>G</value>
    </rating><rating system="Canadian Parental Rating">
      <value>G</value>
    </rating><rating system="Dirección General de Radio, Televisión y Cinematografía">
      <value>A</value>
    </rating><rating system="Australian Classification Board">
      <value>G</value>
    </rating><rating system="Departamento de Justiça, Classificação, Títulos e Qualificação">
      <value>L</value>
    </rating><rating system="Kijkwijzer">
      <value>AL</value>
    </rating>
  </programme><programme channel="FYI-East-US" start="20260416150000 +0500" stop="20260416153000 +0500">
    <title>Tired of Pain? Go Drug-Free</title>
    <sub-title />
    <desc>See how a drug-free patch is helping people find relief-without medication.</desc>
    <category lang="en">Consumer</category>
    <language>en</language>
    <icon src="http://dtil.tmsimg.com/assets/p32384250_st_h10_aa.jpg?w=960&amp;h=540" />
  </programme><programme channel="FYI-East-US" start="20260416153000 +0500" stop="20260416160000 +0500">
    <title>Inogen Portable Oxygen - No More Tanks!</title>
    <sub-title />
    <desc>Regain independence and enjoy greater mobility with the compact design and long-lasting battery of portable oxygen.</desc>
    <category lang="en">Health</category>
    <category lang="en">Consumer</category>
    <category lang="en">Science</category>
    <category lang="en">Medical</category>
    <category lang="en">Technology</category>
    <language>en</language>
    <icon src="http://dtil.tmsimg.com/assets/p17108681_b_h11_ab.jpg?w=960&amp;h=540" />
  </programme><programme channel="FYI-East-US" start="20260416160000 +0500" stop="20260416163000 +0500">
    <title>Joni Table Talk</title>
    <sub-title />
    <desc>Joni and guests tackle a wide range of relevant issues, controversial subjects and hard-hitting news topics with candor and wit.</desc>
    <credits>
      <actor>Joni Lamb</actor>
    </credits><date>2013</date>
    <category lang="en">Religious</category>
    <category lang="en">Talk</category>
    <category lang="en">Community</category>
    <language>en</language>
    <icon src="http://dtil.tmsimg.com/assets/p32105729_b_h8_aa.jpg?w=960&amp;h=540" />
    <rating system="Canadian Parental Rating">
      <value>G</value>
    </rating><rating system="USA Parental Rating">
      <value>TVG</value>
    </rating><rating system="Régie du cinéma">
      <value>G</value>
    </rating><rating system="Australian Classification Board">
      <value>PG</value>
    </rating>
  </programme><programme channel="FYI-East-US" start="20260416163000 +0500" stop="20260416170000 +0500">
    <title>Through the Bible With Les Feldick</title>
    <sub-title />
    <desc>Les Feldick, an Oklahoma farmer and rancher with a special gift for teaching the Bible; his simple and nondenominational approach on the program "Through the Bible with Les Feldick" has reached millions around the world with the Gospel of Grace.</desc>
    <credits>
      <actor>Les Feldick</actor>
    </credits><date>1990</date>
    <category lang="en">Religious</category>
    <language>en</language>
    <icon src="http://dtil.tmsimg.com/assets/p958387_b_h10_ab.jpg?w=960&amp;h=540" />
    <rating system="USA Parental Rating">
      <value>TVG</value>
    </rating><rating system="Canadian Parental Rating">
      <value>G</value>
    </rating><rating system="Régie du cinéma">
      <value>G</value>
    </rating>
  </programme><programme channel="FYI-East-US" start="20260416170000 +0500" stop="20260416173000 +0500">
    <title>Counting Cars</title>
    <sub-title>Fighting Ford, Part 1</sub-title>
    <desc>Danny has a customer who is looking to restore a 1942 Ford truck that saw some action in WWII; Roli and Ryan look at a '71 Duster; Danny gets a 1974 Bronco that isn't all he thought it would be.</desc>
    <episode-num system="onscreen">S4 E19 P1/2</episode-num>
    <credits>
      <actor>Danny Koker</actor>
      <actor>Kevin Mack</actor>
      <actor>Mike "Horny" Henry</actor>
    </credits><date>2015</date>
    <category lang="en">Series</category>
    <category lang="en">Reality</category>
    <category lang="en">Auto</category>
    <language>en</language>
    <icon src="http://dtil.tmsimg.com/assets/p9354925_b_h8_bq.jpg?w=960&amp;h=540" />
    <rating system="USA Parental Rating">
      <value>TVPG</value>
    </rating><rating system="Régie du cinéma">
      <value>G</value>
    </rating><rating system="Freiwillige Selbstkontrolle der Filmwirtschaft">
      <value>12</value>
    </rating><rating system="Canadian Parental Rating">
      <value>PG</value>
    </rating><rating system="Australian Classification Board">
      <value>PG</value>
    </rating><rating system="Kijkwijzer">
      <value>AL</value>
    </rating><rating system="Krajowa Rada Radiofonii i Telewizji">
      <value>12</value>
    </rating><rating system="Departamento de Justiça, Classificação, Títulos e Qualificação">
      <value>A10</value>
    </rating>
  </programme><programme channel="FYI-East-US" start="20260416173000 +0500" stop="20260416180000 +0500">
    <title>Counting Cars</title>
    <sub-title>Fighting Ford, Part 2</sub-title>
    <desc>The shop is restoring a 1942 Ford truck; Danny and Ryan look at a 1929 Ford Roadster; Gary pulls one over on Mike in the paint shop; Danny finds a Corvette and Firebird that might be for sale.</desc>
    <episode-num system="onscreen">S4 E20 P2/2</episode-num>
    <credits>
      <actor>Danny Koker</actor>
      <actor>Kevin Mack</actor>
      <actor>Mike "Horny" Henry</actor>
    </credits><date>2015</date>
    <category lang="en">Series</category>
    <category lang="en">Reality</category>
    <category lang="en">Auto</category>
    <language>en</language>
    <icon src="http://dtil.tmsimg.com/assets/p9354925_b_h8_bq.jpg?w=960&amp;h=540" />
    <rating system="USA Parental Rating">
      <value>TVPG</value>
    </rating><rating system="Canadian Parental Rating">
      <value>PG</value>
    </rating><rating system="Australian Classification Board">
      <value>PG</value>
    </rating><rating system="Régie du cinéma">
      <value>G</value>
    </rating><rating system="Freiwillige Selbstkontrolle der Filmwirtschaft">
      <value>12</value>
    </rating><rating system="Kijkwijzer">
      <value>AL</value>
    </rating><rating system="Departamento de Justiça, Classificação, Títulos e Qualificação">
      <value>A10</value>
    </rating>
  </programme><programme channel="FYI-East-US" start="20260416180000 +0500" stop="20260416183000 +0500">
    <title>Counting Cars</title>
    <sub-title>Don't Tell Danny</sub-title>
    <desc>Mike buys a Smart car and wants to trick it out at the shop; Danny's pal Shane wants to show Danny his new 1955 Chevy; a special project that will take Danny back to when he first got into cars.</desc>
    <episode-num system="onscreen">S4 E12</episode-num>
    <credits>
      <actor>Danny Koker</actor>
    </credits><date>2015</date>
    <category lang="en">Series</category>
    <category lang="en">Reality</category>
    <category lang="en">Auto</category>
    <language>en</language>
    <icon src="http://dtil.tmsimg.com/assets/p9354925_b_h8_bq.jpg?w=960&amp;h=540" />
    <rating system="USA Parental Rating">
      <value>TVPG</value>
    </rating><rating system="Freiwillige Selbstkontrolle der Filmwirtschaft">
      <value>12</value>
    </rating><rating system="Régie du cinéma">
      <value>G</value>
    </rating><rating system="Canadian Parental Rating">
      <value>PG</value>
    </rating><rating system="Australian Classification Board">
      <value>PG</value>
    </rating><rating system="Krajowa Rada Radiofonii i Telewizji">
      <value>12</value>
    </rating><rating system="Kijkwijzer">
      <value>AL</value>
    </rating><rating system="Departamento de Justiça, Classificação, Títulos e Qualificação">
      <value>A10</value>
    </rating>
  </programme><programme channel="FYI-East-US" start="20260416183000 +0500" stop="20260416190000 +0500">
    <title>Counting Cars</title>
    <sub-title>The Return of the Big Twin</sub-title>
    <desc>Ryan is working on a secret project for chopper shop Bones Legacy, while a Chevy Impala that redefines lowrider blinds Mike and Roli; Danny looks into a Satellite Sebring, but has a hard time making a deal.</desc>
    <episode-num system="onscreen">S4 E9</episode-num>
    <credits>
      <actor>Danny Koker</actor>
    </credits><date>2015</date>
    <category lang="en">Series</category>
    <category lang="en">Reality</category>
    <category lang="en">Auto</category>
    <language>en</language>
    <icon src="http://dtil.tmsimg.com/assets/p9354925_b_h8_bq.jpg?w=960&amp;h=540" />
    <rating system="USA Parental Rating">
      <value>TVPG</value>
    </rating><rating system="Freiwillige Selbstkontrolle der Filmwirtschaft">
      <value>12</value>
    </rating><rating system="Régie du cinéma">
      <value>G</value>
    </rating><rating system="Canadian Parental Rating">
      <value>PG</value>
    </rating><rating system="Australian Classification Board">
      <value>PG</value>
    </rating><rating system="Krajowa Rada Radiofonii i Telewizji">
      <value>12</value>
    </rating><rating system="Kijkwijzer">
      <value>AL</value>
    </rating><rating system="Departamento de Justiça, Classificação, Títulos e Qualificação">
      <value>A10</value>
    </rating><rating system="Arcom">
      <value>-10</value>
    </rating>
  </programme><programme channel="FYI-East-US" start="20260416190000 +0500" stop="20260416193000 +0500">
    <title>Counting Cars</title>
    <sub-title>I Want My Caddy Back</sub-title>
    <desc>Kevin's brother would like to sell Danny a 1969 Cadillac, but they can't let Kevin know or else he'll never trust his brother or Danny again; Danny wants to purchase a 1936 Ford Humpback when he's supposed to be shopping for a Rolls-Royce.</desc>
    <episode-num system="onscreen">S4 E5</episode-num>
    <credits>
      <actor>Danny Koker</actor>
      <actor>Kevin Mack</actor>
      <actor>Mike "Horny" Henry</actor>
    </credits><date>2015</date>
    <category lang="en">Series</category>
    <category lang="en">Reality</category>
    <category lang="en">Auto</category>
    <language>en</language>
    <icon src="http://dtil.tmsimg.com/assets/p9354925_b_h8_bq.jpg?w=960&amp;h=540" />
    <rating system="USA Parental Rating">
      <value>TVPG</value>
    </rating><rating system="Freiwillige Selbstkontrolle der Filmwirtschaft">
      <value>12</value>
    </rating><rating system="Canadian Parental Rating">
      <value>PG</value>
    </rating><rating system="Australian Classification Board">
      <value>PG</value>
    </rating><rating system="Régie du cinéma">
      <value>G</value>
    </rating><rating system="Krajowa Rada Radiofonii i Telewizji">
      <value>12</value>
    </rating><rating system="Kijkwijzer">
      <value>AL</value>
    </rating><rating system="Departamento de Justiça, Classificação, Títulos e Qualificação">
      <value>A10</value>
    </rating><rating system="Arcom">
      <value>-10</value>
    </rating>
  </programme><programme channel="FYI-East-US" start="20260416193000 +0500" stop="20260416200000 +0500">
    <title>Counting Cars</title>
    <sub-title>Road Runner Redemption</sub-title>
    <desc>A returning customer requires Danny's help restoring a 1971 Road Runner to give as a celebratory gift to his wife and step-daughter; Mike and Roli settle a debt by gloving up and taking it to the mat.</desc>
    <episode-num system="onscreen">S4 E7</episode-num>
    <credits>
      <actor>Danny Koker</actor>
      <actor>Kevin Mack</actor>
      <actor>Mike "Horny" Henry</actor>
    </credits><date>2015</date>
    <category lang="en">Series</category>
    <category lang="en">Reality</category>
    <category lang="en">Auto</category>
    <language>en</language>
    <icon src="http://dtil.tmsimg.com/assets/p9354925_b_h8_bq.jpg?w=960&amp;h=540" />
    <rating system="USA Parental Rating">
      <value>TVPG</value>
    </rating><rating system="Freiwillige Selbstkontrolle der Filmwirtschaft">
      <value>12</value>
    </rating><rating system="Canadian Parental Rating">
      <value>PG</value>
    </rating><rating system="Australian Classification Board">
      <value>PG</value>
    </rating><rating system="Régie du cinéma">
      <value>G</value>
    </rating><rating system="Krajowa Rada Radiofonii i Telewizji">
      <value>12</value>
    </rating><rating system="Kijkwijzer">
      <value>AL</value>
    </rating><rating system="Departamento de Justiça, Classificação, Títulos e Qualificação">
      <value>A10</value>
    </rating><rating system="Arcom">
      <value>-10</value>
    </rating>
  </programme><programme channel="FYI-East-US" start="20260416200000 +0500" stop="20260416203000 +0500">
    <title>Counting Cars</title>
    <sub-title>Fast and Furry-ous</sub-title>
    <desc>Danny lands a pimp-tastic 1967 Impala, but when it's time to hand the keys over to an important client Danny doesn't think he can let her go; an old friend shows Danny a 1914 Ford that's headed to the Smithsonian.</desc>
    <episode-num system="onscreen">S4 E22</episode-num>
    <credits>
      <actor>Danny Koker</actor>
    </credits><date>2015</date>
    <category lang="en">Series</category>
    <category lang="en">Reality</category>
    <category lang="en">Auto</category>
    <language>en</language>
    <icon src="http://dtil.tmsimg.com/assets/p9354925_b_h8_bq.jpg?w=960&amp;h=540" />
    <rating system="USA Parental Rating">
      <value>TVPG</value>
    </rating><rating system="Freiwillige Selbstkontrolle der Filmwirtschaft">
      <value>12</value>
    </rating><rating system="Arcom">
      <value>-10</value>
    </rating><rating system="Canadian Parental Rating">
      <value>PG</value>
    </rating><rating system="Australian Classification Board">
      <value>PG</value>
    </rating><rating system="Régie du cinéma">
      <value>G</value>
    </rating><rating system="Kijkwijzer">
      <value>AL</value>
    </rating><rating system="Krajowa Rada Radiofonii i Telewizji">
      <value>12</value>
    </rating><rating system="Departamento de Justiça, Classificação, Títulos e Qualificação">
      <value>A10</value>
    </rating>
  </programme><programme channel="FYI-East-US" start="20260416203000 +0500" stop="20260416210000 +0500">
    <title>Counting Cars</title>
    <sub-title>Burning Out</sub-title>
    <desc>Danny has plans for a 1972 Cutlass he hopes to flip; Roli looks for help from the guys to learn to do a burn-out; Danny examines a 1971 Torino whose owner can't seem to put a price on it.</desc>
    <episode-num system="onscreen">S4 E11</episode-num>
    <credits>
      <actor>Danny Koker</actor>
      <actor>Kevin Mack</actor>
      <actor>Mike "Horny" Henry</actor>
    </credits><date>2015</date>
    <category lang="en">Series</category>
    <category lang="en">Reality</category>
    <category lang="en">Auto</category>
    <language>en</language>
    <icon src="http://dtil.tmsimg.com/assets/p9354925_b_h8_bq.jpg?w=960&amp;h=540" />
    <rating system="USA Parental Rating">
      <value>TVPG</value>
    </rating><rating system="Freiwillige Selbstkontrolle der Filmwirtschaft">
      <value>12</value>
    </rating><rating system="Canadian Parental Rating">
      <value>PG</value>
    </rating><rating system="Australian Classification Board">
      <value>PG</value>
    </rating><rating system="Régie du cinéma">
      <value>G</value>
    </rating><rating system="Krajowa Rada Radiofonii i Telewizji">
      <value>12</value>
    </rating><rating system="Kijkwijzer">
      <value>AL</value>
    </rating><rating system="Departamento de Justiça, Classificação, Títulos e Qualificação">
      <value>A10</value>
    </rating>
  </programme><programme channel="FYI-East-US" start="20260416210000 +0500" stop="20260417020000 +0500">
    <title>Live: Barrett-Jackson Auction</title>
    <sub-title>Palm Beach 2026 Day 1 Part 3</sub-title>
    <desc>Collector car auctions return with the Palm Beach Auction, live and exclusive from the South Florida Fairgrounds, West Palm Beach, Fla.</desc>
    <episode-num system="onscreen">S4</episode-num>
    <date>2026</date>
    <category lang="en">Series</category>
    <category lang="en">Auction</category>
    <language>en</language>
    <icon src="http://dtil.tmsimg.com/assets/p18981988_b_h8_aa.jpg?w=960&amp;h=540" />
    <rating system="USA Parental Rating">
      <value>TVPG</value>
    </rating><rating system="Canadian Parental Rating">
      <value>PG</value>
    </rating>
  </programme><programme channel="FYI-East-US" start="20260417020000 +0500" stop="20260417050000 +0500">
    <title>Barrett-Jackson Auction</title>
    <sub-title>Palm Beach 2026 Day 1 Part 3</sub-title>
    <desc>Collector car auctions return with the Palm Beach Auction, live and exclusive from the South Florida Fairgrounds, West Palm Beach, Fla.</desc>
    <episode-num system="onscreen">S4</episode-num>
    <date>2026</date>
    <category lang="en">Series</category>
    <category lang="en">Auction</category>
    <language>en</language>
    <icon src="http://dtil.tmsimg.com/assets/p18981988_b_h8_aa.jpg?w=960&amp;h=540" />
    <rating system="USA Parental Rating">
      <value>TVPG</value>
    </rating><rating system="Canadian Parental Rating">
      <value>PG</value>
    </rating>
  </programme><programme channel="FYI-East-US" start="20260417050000 +0500" stop="20260417060000 +0500">
    <title>Barrett-Jackson Auction</title>
    <sub-title>Palm Beach 2026 Day 1 Part 3</sub-title>
    <desc>Collector car auctions return with the Palm Beach Auction, live and exclusive from the South Florida Fairgrounds, West Palm Beach, Fla.</desc>
    <episode-num system="onscreen">S4</episode-num>
    <date>2026</date>
    <category lang="en">Series</category>
    <category lang="en">Auction</category>
    <language>en</language>
    <icon src="http://dtil.tmsimg.com/assets/p18981988_b_h8_aa.jpg?w=960&amp;h=540" />
    <rating system="USA Parental Rating">
      <value>TVPG</value>
    </rating><rating system="Canadian Parental Rating">
      <value>PG</value>
    </rating>
  </programme><programme channel="FYI-East-US" start="20260417060000 +0500" stop="20260417070000 +0500">
    <title>Barrett-Jackson Auction</title>
    <sub-title>Palm Beach 2026 Day 1 Part 3</sub-title>
    <desc>Collector car auctions return with the Palm Beach Auction, live and exclusive from the South Florida Fairgrounds, West Palm Beach, Fla.</desc>
    <episode-num system="onscreen">S4</episode-num>
    <date>2026</date>
    <category lang="en">Series</category>
    <category lang="en">Auction</category>
    <language>en</language>
    <icon src="http://dtil.tmsimg.com/assets/p18981988_b_h8_aa.jpg?w=960&amp;h=540" />
    <rating system="USA Parental Rating">
      <value>TVPG</value>
    </rating><rating system="Canadian Parental Rating">
      <value>PG</value>
    </rating>
  </programme><programme channel="FYI-East-US" start="20260417070000 +0500" stop="20260417090000 +0500">
    <title>Barrett-Jackson Auction</title>
    <sub-title>Palm Beach 2026 Day 1 Part 3</sub-title>
    <desc>Collector car auctions return with the Palm Beach Auction, live and exclusive from the South Florida Fairgrounds, West Palm Beach, Fla.</desc>
    <episode-num system="onscreen">S4</episode-num>
    <date>2026</date>
    <category lang="en">Series</category>
    <category lang="en">Auction</category>
    <language>en</language>
    <icon src="http://dtil.tmsimg.com/assets/p18981988_b_h8_aa.jpg?w=960&amp;h=540" />
    <rating system="USA Parental Rating">
      <value>TVPG</value>
    </rating><rating system="Canadian Parental Rating">
      <value>PG</value>
    </rating>
  </programme><programme channel="FYI-East-US" start="20260417090000 +0500" stop="20260417100000 +0500">
    <title>Barrett-Jackson Auction</title>
    <sub-title>Palm Beach 2026 Day 1 Part 3</sub-title>
    <desc>Collector car auctions return with the Palm Beach Auction, live and exclusive from the South Florida Fairgrounds, West Palm Beach, Fla.</desc>
    <episode-num system="onscreen">S4</episode-num>
    <date>2026</date>
    <category lang="en">Series</category>
    <category lang="en">Auction</category>
    <language>en</language>
    <icon src="http://dtil.tmsimg.com/assets/p18981988_b_h8_aa.jpg?w=960&amp;h=540" />
    <rating system="USA Parental Rating">
      <value>TVPG</value>
    </rating><rating system="Canadian Parental Rating">
      <value>PG</value>
    </rating>
  </programme><programme channel="FYI-East-US" start="20260417100000 +0500" stop="20260417110000 +0500">
    <title>Barrett-Jackson Auction</title>
    <sub-title>Palm Beach 2026 Day 1 Part 3</sub-title>
    <desc>Collector car auctions return with the Palm Beach Auction, live and exclusive from the South Florida Fairgrounds, West Palm Beach, Fla.</desc>
    <episode-num system="onscreen">S4</episode-num>
    <date>2026</date>
    <category lang="en">Series</category>
    <category lang="en">Auction</category>
    <language>en</language>
    <icon src="http://dtil.tmsimg.com/assets/p18981988_b_h8_aa.jpg?w=960&amp;h=540" />
    <rating system="USA Parental Rating">
      <value>TVPG</value>
    </rating><rating system="Canadian Parental Rating">
      <value>PG</value>
    </rating>
  </programme><programme channel="FYI-East-US" start="20260417110000 +0500" stop="20260417130000 +0500">
    <title>Barrett-Jackson Auction</title>
    <sub-title>Palm Beach 2026 Day 1 Part 3</sub-title>
    <desc>Collector car auctions return with the Palm Beach Auction, live and exclusive from the South Florida Fairgrounds, West Palm Beach, Fla.</desc>
    <episode-num system="onscreen">S4</episode-num>
    <date>2026</date>
    <category lang="en">Series</category>
    <category lang="en">Auction</category>
    <language>en</language>
    <icon src="http://dtil.tmsimg.com/assets/p18981988_b_h8_aa.jpg?w=960&amp;h=540" />
    <rating system="USA Parental Rating">
      <value>TVPG</value>
    </rating><rating system="Canadian Parental Rating">
      <value>PG</value>
    </rating>
  </programme><programme channel="FYI-East-US" start="20260417130000 +0500" stop="20260417133000 +0500">
    <title>Counting Cars</title>
    <sub-title>Fighting Ford, Part 1</sub-title>
    <desc>Danny has a customer who is looking to restore a 1942 Ford truck that saw some action in WWII; Roli and Ryan look at a '71 Duster; Danny gets a 1974 Bronco that isn't all he thought it would be.</desc>
    <episode-num system="onscreen">S4 E19 P1/2</episode-num>
    <credits>
      <actor>Danny Koker</actor>
      <actor>Kevin Mack</actor>
      <actor>Mike "Horny" Henry</actor>
    </credits><date>2015</date>
    <category lang="en">Series</category>
    <category lang="en">Reality</category>
    <category lang="en">Auto</category>
    <language>en</language>
    <icon src="http://dtil.tmsimg.com/assets/p9354925_b_h8_bq.jpg?w=960&amp;h=540" />
    <rating system="USA Parental Rating">
      <value>TVPG</value>
    </rating><rating system="Régie du cinéma">
      <value>G</value>
    </rating><rating system="Freiwillige Selbstkontrolle der Filmwirtschaft">
      <value>12</value>
    </rating><rating system="Canadian Parental Rating">
      <value>PG</value>
    </rating><rating system="Australian Classification Board">
      <value>PG</value>
    </rating><rating system="Kijkwijzer">
      <value>AL</value>
    </rating><rating system="Krajowa Rada Radiofonii i Telewizji">
      <value>12</value>
    </rating><rating system="Departamento de Justiça, Classificação, Títulos e Qualificação">
      <value>A10</value>
    </rating>
  </programme><programme channel="FYI-East-US" start="20260417133000 +0500" stop="20260417140000 +0500">
    <title>Counting Cars</title>
    <sub-title>Fighting Ford, Part 2</sub-title>
    <desc>The shop is restoring a 1942 Ford truck; Danny and Ryan look at a 1929 Ford Roadster; Gary pulls one over on Mike in the paint shop; Danny finds a Corvette and Firebird that might be for sale.</desc>
    <episode-num system="onscreen">S4 E20 P2/2</episode-num>
    <credits>
      <actor>Danny Koker</actor>
      <actor>Kevin Mack</actor>
      <actor>Mike "Horny" Henry</actor>
    </credits><date>2015</date>
    <category lang="en">Series</category>
    <category lang="en">Reality</category>
    <category lang="en">Auto</category>
    <language>en</language>
    <icon src="http://dtil.tmsimg.com/assets/p9354925_b_h8_bq.jpg?w=960&amp;h=540" />
    <rating system="USA Parental Rating">
      <value>TVPG</value>
    </rating><rating system="Canadian Parental Rating">
      <value>PG</value>
    </rating><rating system="Australian Classification Board">
      <value>PG</value>
    </rating><rating system="Régie du cinéma">
      <value>G</value>
    </rating><rating system="Freiwillige Selbstkontrolle der Filmwirtschaft">
      <value>12</value>
    </rating><rating system="Kijkwijzer">
      <value>AL</value>
    </rating><rating system="Departamento de Justiça, Classificação, Títulos e Qualificação">
      <value>A10</value>
    </rating>
  </programme><programme channel="FYI-East-US" start="20260417140000 +0500" stop="20260417143000 +0500">
    <title>Rare Limited Silver</title>
    <sub-title />
    <desc>Secure the lowest mintage Philadelphia Proof Silver Eagle ever issued by the US Mint with this 2026 Congratulations Set Silver Eagle graded PF70UCAM; this coin boasts a minuscule 60,000 mintage limit, housed in a signed First Day of Issue holder.</desc>
    <category lang="en">Consumer</category>
    <language>en</language>
    <icon src="http://dtil.tmsimg.com/assets/p32838703_b_h8_aa.jpg?w=960&amp;h=540" />
  </programme><programme channel="FYI-East-US" start="20260417143000 +0500" stop="20260417150000 +0500">
    <title>Rare Limited Silver</title>
    <sub-title />
    <desc>Secure the lowest mintage Philadelphia Proof Silver Eagle ever issued by the US Mint with this 2026 Congratulations Set Silver Eagle graded PF70UCAM; this coin boasts a minuscule 60,000 mintage limit, housed in a signed First Day of Issue holder.</desc>
    <category lang="en">Consumer</category>
    <language>en</language>
    <icon src="http://dtil.tmsimg.com/assets/p32838703_b_h8_aa.jpg?w=960&amp;h=540" />
  </programme><programme channel="FYI-East-US" start="20260417150000 +0500" stop="20260417153000 +0500">
    <title>1776 Gold Rare Coin</title>
    <sub-title />
    <desc>Celebrate the 250th Anniversary of American Freedom with this Gold 1776-2026 American Gold Eagle graded PF70UCAM. Encapsulated in a 1 of 250 40th Anniversary holder with the First Day of Issue designation, this is a once in a lifetime American coin!</desc>
    <category lang="en">Consumer</category>
    <language>en</language>
    <icon src="http://dtil.tmsimg.com/assets/p32628806_b_h8_aa.jpg?w=960&amp;h=540" />
  </programme><programme channel="FYI-East-US" start="20260417153000 +0500" stop="20260417160000 +0500">
    <title>1776 Gold Rare Coin</title>
    <sub-title />
    <desc>Celebrate the 250th Anniversary of American Freedom with this Gold 1776-2026 American Gold Eagle graded PF70UCAM. Encapsulated in a 1 of 250 40th Anniversary holder with the First Day of Issue designation, this is a once in a lifetime American coin!</desc>
    <category lang="en">Consumer</category>
    <language>en</language>
    <icon src="http://dtil.tmsimg.com/assets/p32628806_b_h8_aa.jpg?w=960&amp;h=540" />
  </programme><programme channel="FYI-East-US" start="20260417160000 +0500" stop="20260417163000 +0500">
    <title>Joni Table Talk</title>
    <sub-title />
    <desc>Joni and guests tackle a wide range of relevant issues, controversial subjects and hard-hitting news topics with candor and wit.</desc>
    <credits>
      <actor>Joni Lamb</actor>
    </credits><date>2013</date>
    <category lang="en">Religious</category>
    <category lang="en">Talk</category>
    <category lang="en">Community</category>
    <language>en</language>
    <icon src="http://dtil.tmsimg.com/assets/p32105729_b_h8_aa.jpg?w=960&amp;h=540" />
    <rating system="Canadian Parental Rating">
      <value>G</value>
    </rating><rating system="USA Parental Rating">
      <value>TVG</value>
    </rating><rating system="Régie du cinéma">
      <value>G</value>
    </rating><rating system="Australian Classification Board">
      <value>PG</value>
    </rating>
  </programme><programme channel="FYI-East-US" start="20260417163000 +0500" stop="20260417170000 +0500">
    <title>Through the Bible With Les Feldick</title>
    <sub-title />
    <desc>Les Feldick, an Oklahoma farmer and rancher with a special gift for teaching the Bible; his simple and nondenominational approach on the program "Through the Bible with Les Feldick" has reached millions around the world with the Gospel of Grace.</desc>
    <credits>
      <actor>Les Feldick</actor>
    </credits><date>1990</date>
    <category lang="en">Religious</category>
    <language>en</language>
    <icon src="http://dtil.tmsimg.com/assets/p958387_b_h10_ab.jpg?w=960&amp;h=540" />
    <rating system="USA Parental Rating">
      <value>TVG</value>
    </rating><rating system="Canadian Parental Rating">
      <value>G</value>
    </rating><rating system="Régie du cinéma">
      <value>G</value>
    </rating>
  </programme><programme channel="FYI-East-US" start="20260417170000 +0500" stop="20260417173000 +0500">
    <title>Counting Cars</title>
    <sub-title>The Full Monte</sub-title>
    <desc>Inspired by the Rat Rods at a local shop, Danny sends the guys out to locate parts for a Count's Kustoms Rat Rod; while on the hunt, Danny gets preoccupied by a beauty of a Bel Air and finds himself on the other side of the bargaining table.</desc>
    <episode-num system="onscreen">S4 E4</episode-num>
    <credits>
      <actor>Danny Koker</actor>
    </credits><date>2015</date>
    <category lang="en">Series</category>
    <category lang="en">Reality</category>
    <category lang="en">Auto</category>
    <language>en</language>
    <icon src="http://dtil.tmsimg.com/assets/p9354925_b_h8_bq.jpg?w=960&amp;h=540" />
    <rating system="USA Parental Rating">
      <value>TVPG</value>
    </rating><rating system="Freiwillige Selbstkontrolle der Filmwirtschaft">
      <value>12</value>
    </rating><rating system="Canadian Parental Rating">
      <value>PG</value>
    </rating><rating system="Australian Classification Board">
      <value>PG</value>
    </rating><rating system="Régie du cinéma">
      <value>G</value>
    </rating><rating system="Krajowa Rada Radiofonii i Telewizji">
      <value>12</value>
    </rating><rating system="Kijkwijzer">
      <value>AL</value>
    </rating><rating system="Departamento de Justiça, Classificação, Títulos e Qualificação">
      <value>A10</value>
    </rating>
  </programme><programme channel="FYI-East-US" start="20260417173000 +0500" stop="20260417180000 +0500">
    <title>Counting Cars</title>
    <sub-title>The King and the Count</sub-title>
    <desc>Kevin and the team get together to make something special for Danny; Danny runs into an old pal and his 1959 Corvette gasser.</desc>
    <episode-num system="onscreen">S4 E6</episode-num>
    <credits>
      <actor>Danny Koker</actor>
      <actor>Kevin Mack</actor>
      <actor>Mike "Horny" Henry</actor>
    </credits><date>2015</date>
    <category lang="en">Series</category>
    <category lang="en">Reality</category>
    <category lang="en">Auto</category>
    <language>en</language>
    <icon src="http://dtil.tmsimg.com/assets/p9354925_b_h8_bq.jpg?w=960&amp;h=540" />
    <rating system="USA Parental Rating">
      <value>TVPG</value>
    </rating><rating system="Freiwillige Selbstkontrolle der Filmwirtschaft">
      <value>12</value>
    </rating><rating system="Canadian Parental Rating">
      <value>PG</value>
    </rating><rating system="Australian Classification Board">
      <value>PG</value>
    </rating><rating system="Régie du cinéma">
      <value>G</value>
    </rating><rating system="Krajowa Rada Radiofonii i Telewizji">
      <value>12</value>
    </rating><rating system="Kijkwijzer">
      <value>AL</value>
    </rating><rating system="Departamento de Justiça, Classificação, Títulos e Qualificação">
      <value>A10</value>
    </rating>
  </programme><programme channel="FYI-East-US" start="20260417180000 +0500" stop="20260417183000 +0500">
    <title>Counting Cars</title>
    <sub-title>The Count of Monte Carlo</sub-title>
    <desc>Danny has to give up his prized 1972 Monte Carlo for one of his biggest clients, and is counting on his team finish the job done in one week; Ryan and Mike go for the ride of their lives in a 1965 Fastback Mustang.</desc>
    <episode-num system="onscreen">S4 E14</episode-num>
    <credits>
      <actor>Danny Koker</actor>
    </credits><date>2015</date>
    <category lang="en">Series</category>
    <category lang="en">Reality</category>
    <category lang="en">Auto</category>
    <language>en</language>
    <icon src="http://dtil.tmsimg.com/assets/p9354925_b_h8_bq.jpg?w=960&amp;h=540" />
    <rating system="USA Parental Rating">
      <value>TVPG</value>
    </rating><rating system="Freiwillige Selbstkontrolle der Filmwirtschaft">
      <value>12</value>
    </rating><rating system="Régie du cinéma">
      <value>G</value>
    </rating><rating system="Canadian Parental Rating">
      <value>PG</value>
    </rating><rating system="Australian Classification Board">
      <value>PG</value>
    </rating><rating system="Kijkwijzer">
      <value>AL</value>
    </rating><rating system="Departamento de Justiça, Classificação, Títulos e Qualificação">
      <value>A10</value>
    </rating>
  </programme><programme channel="FYI-East-US" start="20260417183000 +0500" stop="20260417190000 +0500">
    <title>Counting Cars</title>
    <sub-title>Bucks &amp; Broncos, Part 1</sub-title>
    <desc>Danny sunk a lot of time into a 1967 Ford Bronco, but to make any profit, the shop will have to turn it around quickly; a customer brings in a 1950 Harley Davidson; Danny gets a chance to go for a spin in a 1966 Corvette Sting Ray.</desc>
    <episode-num system="onscreen">S4 E15 P1/2</episode-num>
    <credits>
      <actor>Danny Koker</actor>
      <actor>Kevin Mack</actor>
      <actor>Mike "Horny" Henry</actor>
    </credits><date>2015</date>
    <category lang="en">Series</category>
    <category lang="en">Reality</category>
    <category lang="en">Auto</category>
    <language>en</language>
    <icon src="http://dtil.tmsimg.com/assets/p9354925_b_h8_bq.jpg?w=960&amp;h=540" />
    <rating system="USA Parental Rating">
      <value>TVPG</value>
    </rating><rating system="Freiwillige Selbstkontrolle der Filmwirtschaft">
      <value>12</value>
    </rating><rating system="Régie du cinéma">
      <value>G</value>
    </rating><rating system="Canadian Parental Rating">
      <value>PG</value>
    </rating><rating system="Australian Classification Board">
      <value>PG</value>
    </rating><rating system="Krajowa Rada Radiofonii i Telewizji">
      <value>12</value>
    </rating><rating system="Kijkwijzer">
      <value>AL</value>
    </rating><rating system="Departamento de Justiça, Classificação, Títulos e Qualificação">
      <value>A10</value>
    </rating>
  </programme><programme channel="FYI-East-US" start="20260417190000 +0500" stop="20260417193000 +0500">
    <title>Counting Cars</title>
    <sub-title>Bucks &amp; Broncos, Part 2</sub-title>
    <desc>Danny has a customer ready to buy the 1967 Ford Bronco he's restoring; Mike and Roli settle a score at a gun range; Danny checks out a 1980 fire truck that was a first responder at the tragic Las Vegas MGM fire.</desc>
    <episode-num system="onscreen">S4 E16 P2/2</episode-num>
    <credits>
      <actor>Danny Koker</actor>
      <actor>Kevin Mack</actor>
      <actor>Mike "Horny" Henry</actor>
    </credits><date>2015</date>
    <category lang="en">Series</category>
    <category lang="en">Reality</category>
    <category lang="en">Auto</category>
    <language>en</language>
    <icon src="http://dtil.tmsimg.com/assets/p9354925_b_h8_bq.jpg?w=960&amp;h=540" />
    <rating system="USA Parental Rating">
      <value>TVPG</value>
    </rating><rating system="Freiwillige Selbstkontrolle der Filmwirtschaft">
      <value>12</value>
    </rating><rating system="Canadian Parental Rating">
      <value>PG</value>
    </rating><rating system="Régie du cinéma">
      <value>G</value>
    </rating><rating system="Australian Classification Board">
      <value>PG</value>
    </rating><rating system="Krajowa Rada Radiofonii i Telewizji">
      <value>12</value>
    </rating><rating system="Kijkwijzer">
      <value>AL</value>
    </rating><rating system="Departamento de Justiça, Classificação, Títulos e Qualificação">
      <value>A10</value>
    </rating>
  </programme><programme channel="FYI-East-US" start="20260417193000 +0500" stop="20260417200000 +0500">
    <title>Counting Cars</title>
    <sub-title>A Legend on Two Wheels</sub-title>
    <desc>Danny is asked to make a commemorative bike that honors music legend Les Paul; Mike wants to impress Danny and checks out a 1940 Dodge that's for sale; Danny and Kevin look at a 1964 Galaxie.</desc>
    <episode-num system="onscreen">S4 E17</episode-num>
    <credits>
      <actor>Danny Koker</actor>
      <actor>Kevin Mack</actor>
      <actor>Mike "Horny" Henry</actor>
    </credits><date>2015</date>
    <category lang="en">Series</category>
    <category lang="en">Reality</category>
    <category lang="en">Auto</category>
    <language>en</language>
    <icon src="http://dtil.tmsimg.com/assets/p9354925_b_h8_bq.jpg?w=960&amp;h=540" />
    <rating system="USA Parental Rating">
      <value>TVPG</value>
    </rating><rating system="Freiwillige Selbstkontrolle der Filmwirtschaft">
      <value>12</value>
    </rating><rating system="Canadian Parental Rating">
      <value>PG</value>
    </rating><rating system="Australian Classification Board">
      <value>PG</value>
    </rating><rating system="Régie du cinéma">
      <value>G</value>
    </rating><rating system="Kijkwijzer">
      <value>AL</value>
    </rating><rating system="Departamento de Justiça, Classificação, Títulos e Qualificação">
      <value>A10</value>
    </rating>
  </programme><programme channel="FYI-East-US" start="20260417200000 +0500" stop="20260418030000 +0500">
    <title>Live: Barrett-Jackson Auction</title>
    <sub-title>Palm Beach 2026 Day 2</sub-title>
    <desc>Collector car auctions return with the Palm Beach Auction, live and exclusive from the South Florida Fairgrounds, West Palm Beach, Fla.</desc>
    <episode-num system="onscreen">S4</episode-num>
    <date>2026</date>
    <category lang="en">Series</category>
    <category lang="en">Auction</category>
    <language>en</language>
    <icon src="http://dtil.tmsimg.com/assets/p18981988_b_h8_aa.jpg?w=960&amp;h=540" />
  </programme>
</tv>